Workbook

Sheet 📊 Painel Anual
A1: 💰 PAINEL FINANCEIRO ANUAL — JUN/2025 a JUN/2026
A2: Categoria | B2: 46174 | C2: 46204 | D2: 46235 | E2: 46266 | F2: 46296 | G2: 46327 | H2: 46357 | I2: 46388 | J2: 46419 | K2: 46447 | L2: 46478 | M2: 46508 | N2: 46539 | O2: TOTAL / MÉDIA
A3: 💰 Receita Total | B3: ='jun-26'!E29 -> 4525 | C3: ='Jul-26'!E30 -> 4525 | D3: ='ago-26'!E33 -> 5070 | E3: ='set-26'!E34 -> 5070 | F3: ='Out-26'!E33 -> 5080 | G3: ='Nov-26'!E33 -> 6904 | H3: ='dez -26'!E33 -> 6914 | I3: ='Jan-27'!E28 -> 5000 | J3: ='Fev-27'!E29 -> 5000 | K3: ='Mar-27'!E27 -> 5125 | L3: ='Abr-27'!E29 -> 4275 | M3: ='Mai-27'!E29 -> 4275 | N3: ='Jun-27'!E29 -> 4275 | O3: =SUM(B3:N3) -> 66038
A4: 🔴 Despesas Total | B4: ='jun-26'!E19 -> 2520 | C4: ='Jul-26'!E20 -> 2665 | D4: 20 | E4: ='set-26'!E24 -> 2768 | F4: ='Out-26'!E23 -> 2007 | G4: ='Nov-26'!E23 -> 1696 | H4: ='dez -26'!E23 -> 1848 | I4: ='Jan-27'!E18 -> 1111 | J4: ='Fev-27'!E19 -> 1084 | K4: ='Mar-27'!E17 -> 1084 | L4: ='Abr-27'!E19 -> 3080 | M4: ='Mai-27'!E19 -> 3080 | N4: ='Jun-27'!E19 -> 3080 | O4: =SUM(B4:N4) -> 26043
A5: ✅ Saldo Livre | B5: ='jun-26'!E29-'jun-26'!E19 -> 2005 | C5: ='Jul-26'!E30-'Jul-26'!E20 -> 1860 | D5: ='ago-26'!E33-'ago-26'!E23 -> 1934.8 | E5: ='set-26'!E34-'set-26'!E24 -> 2302 | F5: ='Out-26'!E33-'Out-26'!E23 -> 3073 | G5: ='Nov-26'!E33-'Nov-26'!E23 -> 5208 | H5: ='dez -26'!E33-'dez -26'!E23 -> 5066 | I5: ='Jan-27'!E28-'Jan-27'!E18 -> 3889 | J5: ='Fev-27'!E29-'Fev-27'!E19 -> 3916 | K5: ='Mar-27'!E27-'Mar-27'!E17 -> 4041 | L5: ='Abr-27'!E29-'Abr-27'!E19 -> 1195 | M5: ='Mai-27'!E29-'Mai-27'!E19 -> 1195 | N5: ='Jun-27'!E29-'Jun-27'!E19 -> 1195 | O5: =SUM(B5:N5) -> 36879.8
A7: 📌 Receita Recorrente | B7: ='jun-26'!E29 -> 4525 | C7: ='Jul-26'!E30 -> 4525 | D7: ='ago-26'!E33 -> 5070 | E7: ='set-26'!E34 -> 5070 | F7: ='Out-26'!E33 -> 5080 | G7: ='Nov-26'!E33 -> 6904 | H7: ='dez -26'!E33 -> 6914 | I7: ='Jan-27'!E28 -> 5000 | J7: ='Fev-27'!E29 -> 5000 | K7: ='Mar-27'!E27 -> 5125 | L7: ='Abr-27'!E29 -> 4275 | M7: ='Mai-27'!E29 -> 4275 | N7: ='Jun-27'!E29 -> 4275 | O7: =SUM(B7:N7) -> 66038
A8: 💸 Despesas Fixas E Gerais | B8: ='jun-26'!E19 -> 2520 | C8: ='Jul-26'!E20 -> 2665 | D8: ='ago-26'!E23 -> 3135.2 | E8: ='set-26'!E24 -> 2768 | F8: ='Out-26'!E23 -> 2007 | G8: ='Nov-26'!E23 -> 1696 | H8: ='dez -26'!E23 -> 1848 | I8: ='Jan-27'!E18 -> 1111 | J8: ='Fev-27'!E19 -> 1084 | K8: ='Mar-27'!E17 -> 1084 | L8: ='Abr-27'!E19 -> 3080 | M8: ='Mai-27'!E19 -> 3080 | N8: ='Jun-27'!E19 -> 3080 | O8: =SUM(B8:N8) -> 29158.2
A9: 📈 % Saldo s/ Receita | B9: =IF('jun-26'!E29>0,('jun-26'!E29-'jun-26'!E19)/'jun-26'!E29,0) -> 0.44309392 | C9: =IF('Jul-26'!E30>0,('Jul-26'!E30-'Jul-26'!E20)/'Jul-26'!E30,0) -> 0.41104972 | D9: =IF('ago-26'!E33>0,('ago-26'!E33-'ago-26'!E23)/'ago-26'!E33,0) -> 0.38161736 | E9: =IF('set-26'!E34>0,('set-26'!E34-'set-26'!E24)/'set-26'!E34,0) -> 0.45404339 | F9: =IF('Out-26'!E33>0,('Out-26'!E33-'Out-26'!E23)/'Out-26'!E33,0) -> 0.60492126 | G9: =IF('Nov-26'!E33>0,('Nov-26'!E33-'Nov-26'!E23)/'Nov-26'!E33,0) -> 0.75434531 | H9: =IF('dez -26'!E33>0,('dez -26'!E33-'dez -26'!E23)/'dez -26'!E33,0) -> 0.73271623 | I9: =IF('Jan-27'!E28>0,('Jan-27'!E28-'Jan-27'!E18)/'Jan-27'!E28,0) -> 0.7778 | J9: =IF('Fev-27'!E29>0,('Fev-27'!E29-'Fev-27'!E19)/'Fev-27'!E29,0) -> 0.7832 | K9: =IF('Mar-27'!E27>0,('Mar-27'!E27-'Mar-27'!E17)/'Mar-27'!E27,0) -> 0.7884878 | L9: =IF('Abr-27'!E29>0,('Abr-27'!E29-'Abr-27'!E19)/'Abr-27'!E29,0) -> 0.27953216 | M9: =IF('Mai-27'!E29>0,('Mai-27'!E29-'Mai-27'!E19)/'Mai-27'!E29,0) -> 0.27953216 | N9: =IF('Jun-27'!E29>0,('Jun-27'!E29-'Jun-27'!E19)/'Jun-27'!E29,0) -> 0.27953216 | O9: =AVERAGE(B9:N9) -> 0.53614396

Sheet 📈 Investimentos
A1: 📈 CONTROLE DE INVESTIMENTOS — JUN/2026 a JUL/2028
A2: ⚙️ PREMISSAS — Altere os valores em azul
A3: Receita recorrente mensal (R$) | B3: 5470 | C3: Sem receitas não-recorrentes
A4: Despesas mensais totais (R$) | B4: 2660 | C4: Fixas + Gerais estimadas
A5: % destinado a investimentos | B5: 0.5 | C5: Regra 50/30/20
A6: Rendimento mensal (CDB/Selic) | B6: 0.0115 | C6: ~1,16%/mês ≈ 14,%/ano
A7: Meta reserva de emergência (R$) | B7: 10000 | C7: meta para novembro
A9: Mês | B9: Data | C9: Aporte (R$) | D9: Rendimento (R$) | E9: Saldo Acum. (R$) | F9: Meta Emerg. (%) | G9: Status | H9: Despesas Mensais (R$) | I9: Saldo Livre Mês (R$) | J9: C2
A10: 46174 | B10: 46174 | C10: 0 | D10: =C10*$B$6 -> 0 | E10: =C10+D10 -> 0 | F10: =E10/$B$7 -> 0 | G10: =IF(E10>=$B$7,"✅ Meta atingida",IF(E10>=$B$7*0.5,"🟡 Meio caminho","🔴 Em construção")) -> 🔴 Em construção | H10: =$B$4 -> 2660 | I10: =$B$3-$B$4 -> 2810 | J10: 0
A11: 46204 | B11: 45839 | C11: 0 | D11: =(E10+C11)*$B$6 -> 0 | E11: =E10+C11+D11 -> 0 | F11: =E11/$B$7 -> 0 | G11: =IF(E11>=$B$7,"✅ Meta atingida",IF(E11>=$B$7*0.5,"🟡 Meio caminho","🔴 Em construção")) -> 🔴 Em construção | H11: =$B$4 -> 2660 | I11: =$B$3-$B$4 -> 2810 | J11: 0
A12: 46235 | B12: 45899 | C12: 400 | D12: =(E11+C12)*$B$6 -> 4.6 | E12: 500 | F12: =E12/$B$7 -> 0.05 | G12: =IF(E12>=$B$7,"✅ Meta atingida",IF(E12>=$B$7*0.5,"🟡 Meio caminho","🔴 Em construção")) -> 🔴 Em construção | H12: =$B$4 -> 2660 | I12: =$B$3-$B$4 -> 2810 | J12: 0
A13: 46266 | B13: 46295 | C13: 2000 | D13: =(E12+C13)*$B$6 -> 28.75 | E13: =E12+C13+D13 -> 2528.75 | F13: =E13/$B$7 -> 0.252875 | G13: =IF(E13>=$B$7,"✅ Meta atingida",IF(E13>=$B$7*0.5,"🟡 Meio caminho","🔴 Em construção")) -> 🔴 Em construção | H13: =$B$4 -> 2660 | I13: =$B$3-$B$4 -> 2810 | J13: 1000
A14: 46296 | B14: 46325 | C14: 2000 | D14: =(E13+C14)*$B$6 -> 52.080625 | E14: =E13+C14+D14 -> 4580.8306 | F14: =E14/$B$7 -> 0.45808306 | G14: =IF(E14>=$B$7,"✅ Meta atingida",IF(E14>=$B$7*0.5,"🟡 Meio caminho","🔴 Em construção")) -> 🔴 Em construção | H14: =$B$4 -> 2660 | I14: =$B$3-$B$4 -> 2810 | J14: 1000
A15: 46327 | B15: 46356 | C15: 3000 | D15: =(E14+C15)*$B$6 -> 87.179552 | E15: =E14+C15+D15 -> 7668.0102 | F15: =E15/$B$7 -> 0.76680102 | G15: =IF(E15>=$B$7,"✅ Meta atingida",IF(E15>=$B$7*0.5,"🟡 Meio caminho","🔴 Em construção")) -> 🟡 Meio caminho | H15: =$B$4 -> 2660 | I15: =$B$3-$B$4 -> 2810 | J15: 1000
A16: 46357 | B16: 46386 | C16: 3000 | D16: =(E15+C16)*$B$6 -> 122.68212 | E16: =E15+C16+D16 -> 10790.692 | F16: =E16/$B$7 -> 1.0790692 | G16: =IF(E16>=$B$7,"✅ Meta atingida",IF(E16>=$B$7*0.5,"🟡 Meio caminho","🔴 Em construção")) -> ✅ Meta atingida | H16: =$B$4 -> 2660 | I16: =$B$3-$B$4 -> 2810 | J16: 1000
A17: 46388 | B17: 46023 | C17: 3000 | D17: =(E16+C17)*$B$6 -> 158.59296 | E17: =E16+C17+D17 -> 13949.285 | F17: =E17/$B$7 -> 1.3949285 | G17: =IF(E17>=$B$7,"✅ Meta atingida",IF(E17>=$B$7*0.5,"🟡 Meio caminho","🔴 Em construção")) -> ✅ Meta atingida | H17: =$B$4 -> 2660 | I17: =$B$3-$B$4 -> 2810 | J17: 1000
A18: 46419 | B18: 46054 | C18: 2000 | D18: =(E17+C18)*$B$6 -> 183.41678 | E18: =E17+C18+D18 -> 16132.702 | F18: =E18/$B$7 -> 1.6132702 | G18: =IF(E18>=$B$7,"✅ Meta atingida",IF(E18>=$B$7*0.5,"🟡 Meio caminho","🔴 Em construção")) -> ✅ Meta atingida | H18: =$B$4 -> 2660 | I18: =$B$3-$B$4 -> 2810 | J18: 1000
A19: 46447 | B19: 46082 | C19: 3500 | D19: =(E18+C19)*$B$6 -> 225.77607 | E19: =E18+C19+D19 -> 19858.478 | F19: =E19/$B$7 -> 1.9858478 | G19: =IF(E19>=$B$7,"✅ Meta atingida",IF(E19>=$B$7*0.5,"🟡 Meio caminho","🔴 Em construção")) -> ✅ Meta atingida | H19: =$B$4 -> 2660 | I19: =$B$3-$B$4 -> 2810 | J19: 1000
A20: 46478 | B20: 46113 | C20: 2000 | D20: =(E19+C20)*$B$6 -> 251.3725 | E20: =E19+C20+D20 -> 22109.851 | F20: =E20/$B$7 -> 2.2109851 | G20: =IF(E20>=$B$7,"✅ Meta atingida",IF(E20>=$B$7*0.5,"🟡 Meio caminho","🔴 Em construção")) -> ✅ Meta atingida | H20: =$B$4 -> 2660 | I20: =$B$3-$B$4 -> 2810 | J20: 1000
A21: 46508 | B21: 46143 | C21: 2000 | D21: =(E20+C21)*$B$6 -> 277.26328 | E21: =E20+C21+D21 -> 24387.114 | F21: =E21/$B$7 -> 2.4387114 | G21: =IF(E21>=$B$7,"✅ Meta atingida",IF(E21>=$B$7*0.5,"🟡 Meio caminho","🔴 Em construção")) -> ✅ Meta atingida | H21: =$B$4 -> 2660 | I21: =$B$3-$B$4 -> 2810 | J21: 1000
A22: 46539 | B22: 46174 | C22: 2000 | D22: =(E21+C22)*$B$6 -> 303.45181 | E22: =E21+C22+D22 -> 26690.566 | F22: =E22/$B$7 -> 2.6690566 | G22: =IF(E22>=$B$7,"✅ Meta atingida",IF(E22>=$B$7*0.5,"🟡 Meio caminho","🔴 Em construção")) -> ✅ Meta atingida | H22: =$B$4 -> 2660 | I22: =$B$3-$B$4 -> 2810 | J22: 1000
A23: 46569 | B23: 46204 | C23: 2000 | D23: =(E22+C23)*$B$6 -> 329.94151 | E23: =E22+C23+D23 -> 29020.507 | F23: =E23/$B$7 -> 2.9020507 | G23: =IF(E23>=$B$7,"✅ Meta atingida",IF(E23>=$B$7*0.5,"🟡 Meio caminho","🔴 Em construção")) -> ✅ Meta atingida | H23: =$B$4 -> 2660 | I23: =$B$3-$B$4 -> 2810 | J23: 1000
A24: 46600 | B24: 46235 | C24: 2000 | D24: =(E23+C24)*$B$6 -> 356.73583 | E24: =E23+C24+D24 -> 31377.243 | F24: =E24/$B$7 -> 3.1377243 | G24: =IF(E24>=$B$7,"✅ Meta atingida",IF(E24>=$B$7*0.5,"🟡 Meio caminho","🔴 Em construção")) -> ✅ Meta atingida | H24: =$B$4 -> 2660 | I24: =$B$3-$B$4 -> 2810 | J24: 1000
... A49: 47362 | B49: 46266 | C49: 2014 | D49: =(E48+C49)*$B$6 -> 1203.0859 | E49: =E48+C49+D49 -> 105819.25 | F49: =E49/$B$7 -> 10.581925 | G49: =IF(E49>=$B$7,"✅ Meta atingida",IF(E49>=$B$7*0.5,"🟡 Meio caminho","🔴 Em construção")) -> ✅ Meta atingida | H49: =$B$4 -> 2660 | I49: =$B$3-$B$4 -> 2810 | J49: 1000
A50: 010/2029 | B50: 46296 | C50: 2015 | D50: =(E49+C50)*$B$6 -> 1240.0939 | E50: =E49+C50+D50 -> 109074.35 | F50: =E50/$B$7 -> 10.907435 | G50: =IF(E50>=$B$7,"✅ Meta atingida",IF(E50>=$B$7*0.5,"🟡 Meio caminho","🔴 Em construção")) -> ✅ Meta atingida | H50: =$B$4 -> 2660 | I50: =$B$3-$B$4 -> 2810 | J50: 1000
A51: 47423 | B51: 46327 | C51: 2016 | D51: =(E50+C51)*$B$6 -> 1277.539 | E51: =E50+C51+D51 -> 112367.89 | F51: =E51/$B$7 -> 11.236789 | G51: =IF(E51>=$B$7,"✅ Meta atingida",IF(E51>=$B$7*0.5,"🟡 Meio caminho","🔴 Em construção")) -> ✅ Meta atingida | H51: =$B$4 -> 2660 | I51: =$B$3-$B$4 -> 2810 | J51: 1000
A52: 47453 | B52: 46357 | C52: 2017 | D52: =(E51+C52)*$B$6 -> 1315.4262 | E52: =E51+C52+D52 -> 115700.31 | F52: =E52/$B$7 -> 11.570031 | G52: =IF(E52>=$B$7,"✅ Meta atingida",IF(E52>=$B$7*0.5,"🟡 Meio caminho","🔴 Em construção")) -> ✅ Meta atingida | H52: =$B$4 -> 2660 | I52: =$B$3-$B$4 -> 2810 | J52: 1000
A53: 47484 | B53: 46388 | C53: 2018 | D53: =(E52+C53)*$B$6 -> 1353.7606 | E53: =E52+C53+D53 -> 119072.07 | F53: =E53/$B$7 -> 11.907207 | G53: =IF(E53>=$B$7,"✅ Meta atingida",IF(E53>=$B$7*0.5,"🟡 Meio caminho","🔴 Em construção")) -> ✅ Meta atingida | H53: =$B$4 -> 2660 | I53: =$B$3-$B$4 -> 2810 | J53: 1000
A54: 47515 | B54: 46419 | C54: 2019 | D54: =(E53+C54)*$B$6 -> 1392.5473 | E54: =E53+C54+D54 -> 122483.62 | F54: =E54/$B$7 -> 12.248362 | G54: =IF(E54>=$B$7,"✅ Meta atingida",IF(E54>=$B$7*0.5,"🟡 Meio caminho","🔴 Em construção")) -> ✅ Meta atingida | H54: =$B$4 -> 2660 | I54: =$B$3-$B$4 -> 2810 | J54: 1000
A55: 47543 | B55: 46447 | C55: 2020 | D55: =(E54+C55)*$B$6 -> 1431.7916 | E55: =E54+C55+D55 -> 125935.41 | F55: =E55/$B$7 -> 12.593541 | G55: =IF(E55>=$B$7,"✅ Meta atingida",IF(E55>=$B$7*0.5,"🟡 Meio caminho","🔴 Em construção")) -> ✅ Meta atingida | H55: =$B$4 -> 2660 | I55: =$B$3-$B$4 -> 2810 | J55: 1000
A56: 47574 | B56: 46478 | C56: 2021 | D56: =(E55+C56)*$B$6 -> 1471.4987 | E56: =E55+C56+D56 -> 129427.91 | F56: =E56/$B$7 -> 12.942791 | G56: =IF(E56>=$B$7,"✅ Meta atingida",IF(E56>=$B$7*0.5,"🟡 Meio caminho","🔴 Em construção")) -> ✅ Meta atingida | H56: =$B$4 -> 2660 | I56: =$B$3-$B$4 -> 2810 | J56: 1000
A57: 47604 | B57: 46508 | C57: 2022 | D57: =(E56+C57)*$B$6 -> 1511.674 | E57: =E56+C57+D57 -> 132961.58 | F57: =E57/$B$7 -> 13.296158 | G57: =IF(E57>=$B$7,"✅ Meta atingida",IF(E57>=$B$7*0.5,"🟡 Meio caminho","🔴 Em construção")) -> ✅ Meta atingida | H57: =$B$4 -> 2660 | I57: =$B$3-$B$4 -> 2810 | J57: 1000
A58: 47635 | B58: 46539 | C58: 2023 | D58: =(E57+C58)*$B$6 -> 1552.3227 | E58: =E57+C58+D58 -> 136536.91 | F58: =E58/$B$7 -> 13.653691 | G58: =IF(E58>=$B$7,"✅ Meta atingida",IF(E58>=$B$7*0.5,"🟡 Meio caminho","🔴 Em construção")) -> ✅ Meta atingida | H58: =$B$4 -> 2660 | I58: =$B$3-$B$4 -> 2810 | J58: 1000
A59: 47665 | B59: 45839 | C59: 2024 | D59: =(E58+C59)*$B$6 -> 1593.4504 | E59: =E58+C59+D59 -> 140154.36 | F59: =E59/$B$7 -> 14.015436 | G59: =IF(E59>=$B$7,"✅ Meta atingida",IF(E59>=$B$7*0.5,"🟡 Meio caminho","🔴 Em construção")) -> ✅ Meta atingida | H59: =$B$4 -> 2660 | I59: =$B$3-$B$4 -> 2810 | J59: 1000
A60: 47696 | B60: 45870 | C60: 2025 | D60: =(E59+C60)*$B$6 -> 1635.0626 | E60: =E59+C60+D60 -> 143814.42 | F60: =E60/$B$7 -> 14.381442 | G60: =IF(E60>=$B$7,"✅ Meta atingida",IF(E60>=$B$7*0.5,"🟡 Meio caminho","🔴 Em construção")) -> ✅ Meta atingida | H60: =$B$4 -> 2660 | I60: =$B$3-$B$4 -> 2810 | J60: 1000
A61: 47727 | B61: 45901 | C61: 2026 | D61: =(E60+C61)*$B$6 -> 1677.1648 | E61: =E60+C61+D61 -> 147517.58 | F61: =E61/$B$7 -> 14.751758 | G61: =IF(E61>=$B$7,"✅ Meta atingida",IF(E61>=$B$7*0.5,"🟡 Meio caminho","🔴 Em construção")) -> ✅ Meta atingida | H61: =$B$4 -> 2660 | I61: =$B$3-$B$4 -> 2810 | J61: 1000
A62: 47757 | B62: 45931 | C62: 2027 | D62: =(E61+C62)*$B$6 -> 1719.7627 | E62: =E61+C62+D62 -> 151264.35 | F62: =E62/$B$7 -> 15.126435 | G62: =IF(E62>=$B$7,"✅ Meta atingida",IF(E62>=$B$7*0.5,"🟡 Meio caminho","🔴 Em construção")) -> ✅ Meta atingida | H62: =$B$4 -> 2660 | I62: =$B$3-$B$4 -> 2810 | J62: 1000
... A72: 48061 | B72: 46235 | C72: 2037 | D72: =(E71+C72)*$B$6 -> 2174.2909 | E72: =E71+C72+D72 -> 191243.07 | F72: =E72/$B$7 -> 19.124307 | G72: =IF(E72>=$B$7,"✅ Meta atingida",IF(E72>=$B$7*0.5,"🟡 Meio caminho","🔴 Em construção")) -> ✅ Meta atingida | H72: =$B$4 -> 2660 | I72: =$B$3-$B$4 -> 2810 | J72: 1000
A73: TOTAL ACUMULADO | C73: =SUM(C10:C72) -> 130103 | D73: =SUM(D10:D72) -> 61044.669 | E73: =E72 -> 191243.07 | F73: =F72 -> 19.124307 | G73: =IF(E73>=$B$7,"✅ Meta atingida",IF(E73>=$B$7*0.5,"🟡 Meio caminho","🔴 Em construção")) -> ✅ Meta atingida | J73: =SUM(J10:J72) -> 60000

Sheet jun-26
A1: 💰 FINANÇAS — JUN/2026
A2: 💰 RECEITA TOTAL | C2: 🔴 DESPESAS TOTAL | E2: ✅ SALDO LIVRE | G2: 📊 % SALDO / RECEITA
A3: =E29 -> 4525 | C3: =E19 -> 2520 | E3: =E29-E19 -> 2005 | G3: =IF(E29>0,(E29-E19)/E29,0) -> 0.44309392
A5: 🔴 DESPESAS — Jun/2025
A6: Data | B6: Descrição | C6: Parcela | D6: Tipo | E6: Valor (R$) | F6: Pago? | G6: Obs.
A7: 06/25 | B7: Neon Fasomim | C7: 1/3 | D7: Parcelado | E7: 86
A8: 06/25 | B8: Plano Cecília | D8: Fixo | E8: 216
A9: 06/25 | B9: Água / Esgoto | D9: Fixo | E9: 230
A10: 06/25 | B10: Energia | D10: Fixo | E10: 95
A11: 06/25 | B11: Celular TIM | D11: Fixo | E11: 120
A12: 06/25 | B12: Plano NENA | D12: Fixo | E12: 288
A13: 06/25 | B13: Internet Casa | D13: Fixo | E13: 135
A17: Total Fixas/Parc. | E17: =SUM(E7:E16) -> 1170
A18: Despesas Gerais (est.) | E18: 1350
A19: TOTAL DESPESAS MÊS | E19: =E17+E18 -> 2520
A21: 🟢 RECEITAS — Jun/2026
A22: Data | B22: Descrição | C22: Parcela | D22: Tipo | E22: Valor (R$) | F22: Recebido? | G22: Obs.
A23: 06/25 | B23: Apartamento Rafa | C23: — | D23: Fixo | E23: 1475
A24: 06/25 | B24: Salário Rafa | C24: — | D24: Fixo | E24: 1300
A25: 06/25 | B25: Salário Gabi | C25: — | D25: Fixo | E25: 1500
A26: 06/25 | B26: Eliane Casa | C26: — | D26: Fixo | E26: 250
A29: TOTAL RECEITAS | E29: =SUM(E23:E28) -> 4525
A31: 💡 ANÁLISE RÁPIDA DO MÊS
A32: Saldo do mês: | E32: =E29-E19 -> 2005
A33: Aporte sugerido (50%): | E33: =0.7*(E29-E19) -> 1403.5
A34: Reserva de emergência: | E34: =E19/6 -> 420

Sheet Jul-26
A1: 💰 FINANÇAS — JUL/2025
A2: 💰 RECEITA TOTAL | C2: 🔴 DESPESAS TOTAL | E2: ✅ SALDO LIVRE | G2: 📊 % SALDO / RECEITA
A3: =E30 -> 4525 | C3: =E20 -> 2665 | E3: =E30-E20 -> 1860 | G3: =IF(E30>0,(E30-E20)/E30,0) -> 0.41104972
A5: 🔴 DESPESAS — Jul/2025
A6: Data | B6: Descrição | C6: Parcela | D6: Tipo | E6: Valor (R$) | F6: Pago? | G6: Obs.
A7: 46204 | B7: Neon Fasomim | C7: 0.66666667 | D7: Parcelado | E7: 86
A8: 46204 | B8: Neon Iasmim | C8: 0.125 | D8: Parcelado | E8: 145
A9: 46204 | B9: Plano Cecília | D9: Fixo | E9: 216
A10: 46204 | B10: Água / Esgoto | D10: Fixo | E10: 230
A11: 46204 | B11: Energia | D11: Fixo | E11: 95
A12: 46204 | B12: Celular TIM | D12: Fixo | E12: 120
A13: 46204 | B13: Plano NENA | D13: Fixo | E13: 288
A14: 46204 | B14: Internet Casa | D14: Fixo | E14: 135
A18: Total Fixas/Parc. | E18: =SUM(E7:E17) -> 1315
A19: Despesas Gerais (est.) | E19: 1350
A20: TOTAL DESPESAS MÊS | E20: =E18+E19 -> 2665
A22: 🟢 RECEITAS — Jul/2025
A23: Data | B23: Descrição | C23: Parcela | D23: Tipo | E23: Valor (R$) | F23: Recebido? | G23: Obs.
A24: 07/25 | B24: Apartamento Rafa | C24: — | D24: Fixo | E24: 1475
A25: 07/25 | B25: Salário Rafa | C25: — | D25: Fixo | E25: 1300
A26: 07/25 | B26: Salário Gabi | C26: — | D26: Fixo | E26: 1500
A27: 07/25 | B27: Eliane Casa | C27: — | D27: Fixo | E27: 250
A30: TOTAL RECEITAS | E30: =SUM(E24:E29) -> 4525
A32: 💡 ANÁLISE RÁPIDA DO MÊS
A33: Saldo do mês: | E33: =E30-E20 -> 1860
A34: Aporte sugerido (20%): | E34: =0.7*(E30-E20) -> 1302
A35: Reserva de emergência: | E35: =E20/6 -> 444.16667

Sheet ago-26
A1: 💰 FINANÇAS — AGO/26
A2: 💰 RECEITA TOTAL | C2: 🔴 DESPESAS TOTAL | E2: ✅ SALDO LIVRE | G2: 📊 % SALDO / RECEITA
A3: =E33 -> 5070 | C3: =E23 -> 3135.2 | E3: =E33-E23 -> 1934.8 | G3: =IF(E33>0,(E33-E23)/E33,0) -> 0.38161736
A5: 🔴 DESPESAS — ago/2026
A6: Data | B6: Descrição | C6: Parcela | D6: Tipo | E6: Valor (R$) | F6: dia de pagamento | G6: Obs. | H6: status
A7: 46235 | B7: GUARDA ROUPA | C7: 3 DE 12 | D7: PARCELADO | E7: 60 | F7: 46254 | G7: CARTAO IASMIM | H7: pago | I7: ok
A8: 46235 | B8: PERFUMES | D8: ULTIMA | E8: 143 | F8: 46254 | G8: BOTICARIO | H8: pago | I8: ok
A9: 46235 | B9: Plano Cecília | D9: FIXO | E9: 250 | F9: 46254 | H9: pago | I9: ok
A10: 46235 | B10: CREDICARD | D10: FIXO | E10: 200 | F10: 46254 | H10: pago | I10: ok
A11: 46235 | B11: SOFA | C11: 4 DE 6 | D11: PARCELADO | E11: 288 | F11: 46254 | G11: CARTAO INGRID | H11: pago | I11: ok
A12: 46235 | B12: CARTAO AMERICANAS | E12: 200 | F12: 46265 | H12: pago | I12: ok
A13: 46236 | B13: Internet Casa | D13: FIXO | E13: 145 | F13: 46254 | G13: TANSPORTE RAFA E GABI | H13: pago | I13: =SUM(E7:E14) -> 1417.2
A14: 46235 | B14: TRASPORTE DE 20A31 | E14: 131.2 | F14: 46254 | H14: pago | I14: ok
A15: 46235 | E15: 250 | F15: 46262 | H15: pago | I15: okj
A16: 46235 | B16: Plano NENA | D16: FIXO | E16: 288 | F16: 46265 | H16: pago | I16: ok
A17: 46235 | B17: luz e agua | D17: fixo | E17: 200 | F17: 46265 | H17: pago | I17: ok
A18: 46235 | B18: Celular TIM | D18: FIXO | E18: 140 | F18: 46265 | G18: RAFAH E GABRIELA | H18: pago | I18: ok
A19: 46236 | B19: gabriela | D19: FIXO | E19: 100 | F19: 46265 | H19: pago | I19: ok
F20: 46265 | H20: ate aqui-------->>>>
A21: Despesas Gerais (est.) | E21: 400 | F21: 46262 | I21: =SUM(E16:E21) -> 1128
A22: total geral | E22: =SUM(E8:E21) -> 2735.2 | L22: =450+2200-728-400 -> 1522
A23: TOTAL DESPESAS MÊS | E23: =E21+E22 -> 3135.2
A25: 🟢 RECEITAS — ago /2026
A26: Data | B26: Descrição | C26: Parcela | D26: Tipo | E26: Valor (R$) | F26: Recebido? | G26: Obs.
A27: 09/25 | B27: adiantamento rafa e gabi | C27: — | D27: Fixo | E27: 2870
A28: 09/25 | B28: Salário Rafa e gabi | C28: — | D28: Fixo | E28: 2200
A29: 09/25 | B29: eliane e marcio agua e luz | C29: — | D29: Fixo
B30: resgate investimento
A33: TOTAL RECEITAS | E33: =SUM(E27:E32) -> 5070
A35: 💡 ANÁLISE RÁPIDA DO MÊS
A36: Saldo do mês: | E36: =E33-E23 -> 1934.8
A37: Aporte sugerido (20%): | E37: =0.7*(E33-E23) -> 1354.36
A38: Reserva de emergência: | E38: =E23/6 -> 522.53333

Sheet set-26
A1: 💰 FINANÇAS — SET/2025
A2: 💰 RECEITA TOTAL | C2: 🔴 DESPESAS TOTAL | E2: ✅ SALDO LIVRE | I2: 📊 % SALDO / RECEITA
A3: =E34 -> 5070 | C3: =E24 -> 2768 | E3: =E34-E24 -> 2302 | I3: =IF(E34>0,(E34-E24)/E34,0) -> 0.45404339
A5: 🔴 DESPESAS — Set/2025
A6: Data | B6: Descrição | C6: Parcela | D6: Tipo | E6: Valor (R$) | F6: dia | H6: Pago? | I6: Obs.
A7: 09/25 | B7: GUARDA ROUPA | C7: 4 DE 12 | D7: PARCELADO | E7: 60 | F7: 46285 | I7: CARTAO IASMIM
A8: 09/25 | B8: CARTAO TRANSPORTE | E8: 200 | F8: 46285
A9: 09/25 | B9: SOFA | C9: 5 DE 6 | D9: PARCELADO | E9: 288 | F9: 46285 | I9: INGRID
A10: 09/25 | B10: INGRID | E10: 100 | F10: 46285 | I10: INGRID
A11: 09/25 | B11: GAS | E11: 65 | F11: 46285 | I11: IASMIM
B12: Água / luz | D12: FIXO | E12: 200 | F12: 46285 | K12: =SUM(E6:E14) -> 1500
A13: 09/25 | B13: Plano Cecília | D13: FIXO | E13: 240 | F13: 46285 | I13: HAP VIDA
B14: COMPRAS | E14: 347
A15: 09/25 | B15: Celular TIM | D15: FIXO | E15: 140 | F15: 46295 | I15: TIM
A16: 09/25 | B16: Plano NENA | D16: FIXO | E16: 288 | F16: 46295 | I16: HAP VIDA
A17: 09/25 | B17: Internet Casa | D17: FIXO | E17: 100 | F17: 46295 | I17: CLARO
A18: 09/25 | B18: CARTAO IASMIM | D18: FIXO | E18: 540 | F18: 46295
A19: 09/25 | B19: AMERICANAS | D19: FIXO | E19: 200 | F19: 46295 | K19: =SUM(E15:E21) -> 1368
A20: 09/25 | B20: Água / luz | D20: FIXO | E20: ok | F20: 46295
B21: GABRIELA | E21: 100 | F21: 46295
A22: Total Fixas/Parc. | E22: =SUM(E7:E19) -> 2768
A23: Despesas Gerais (est.)
A24: TOTAL DESPESAS MÊS | E24: =E22+E23 -> 2768
A26: 🟢 RECEITAS — Set/2025
A27: Data | B27: Descrição | C27: Parcela | D27: Tipo | E27: Valor (R$) | H27: Recebido? | I27: Obs.
A28: 09/25 | B28: adiantamento rafa e gabi | C28: — | D28: Fixo | E28: 2870
A29: 09/25 | B29: Salário Rafa e gabi | C29: — | D29: Fixo | E29: 2200
D30: Fixo
A34: TOTAL RECEITAS | E34: =SUM(E28:E33) -> 5070
A36: 💡 ANÁLISE RÁPIDA DO MÊS
A37: Saldo do mês: | E37: =E34-E24 -> 2302
A38: Aporte sugerido (20%): | E38: =0.7*(E34-E24) -> 1611.4
A39: Reserva de emergência: | E39: =E24/6 -> 461.33333

Sheet Out-26
A1: 💰 FINANÇAS — OUT/2025
A2: 💰 RECEITA TOTAL | C2: 🔴 DESPESAS TOTAL | E2: ✅ SALDO LIVRE | G2: 📊 % SALDO / RECEITA
A3: =E33 -> 5080 | C3: =E23 -> 2007 | E3: =E33-E23 -> 3073 | G3: =IF(E33>0,(E33-E23)/E33,0) -> 0.60492126
A5: 🔴 DESPESAS — Out/2026
A6: Data | B6: Descrição | C6: Parcela | D6: Tipo | E6: Valor (R$) | F6: Pago? | G6: Obs.
B7: GUARDA ROUPA | C7: 5 DE 12 | D7: PARCELADO | E7: 60 | G7: CARTAO IASMIM
B8: CARTAO NEON IASMIM | D8: FATURA MÊS | E8: 458
A9: 10/25 | B9: Plano Cecília | D9: FIXO | E9: 250
A10: 10/25 | B10: Água / Esgoto | D10: FIXO | E10: 178
A11: 10/25 | B11: SOFA | C11: 6 DE 6 | D11: PARCELADO | E11: 288 | G11: CARTAO INGRID
A12: 10/25 | B12: Celular TIM | D12: FIXO | E12: 140 | G12: RAFAH E GABRIELA
A13: 10/25 | B13: Plano NENA | D13: FIXO | E13: 288
A14: 10/25 | B14: Internet Casa | D14: FIXO | E14: 145
B15: CREDICARD | D15: FIXO | E15: 200
E19: 0
E20: 0
A21: Total Fixas/Parc. | E21: =SUM(E7:E19) -> 2007
A22: Despesas Gerais (est.)
A23: TOTAL DESPESAS MÊS | E23: =E21+E22 -> 2007
A25: 🟢 RECEITAS — Out/2026
A26: Data | B26: Descrição | C26: Parcela | D26: Tipo | E26: Valor (R$) | F26: Recebido? | G26: Obs.
A27: 10/25 | B27: Apartamento Rafa | C27: — | D27: Fixo | E27: 2870
A28: 10/25 | B28: Salário Rafa | C28: — | D28: Fixo | E28: 2210
A33: TOTAL RECEITAS | E33: =SUM(E27:E32) -> 5080
A35: 💡 ANÁLISE RÁPIDA DO MÊS
A36: Saldo do mês: | E36: =E33-E23 -> 3073
A37: Aporte sugerido (20%): | E37: =0.7*(E33-E23) -> 2151.1
A38: Reserva de emergência: | E38: =E23/6 -> 334.5

Sheet Nov-26
A1: 💰 FINANÇAS — NOV/2025
A2: 💰 RECEITA TOTAL | C2: 🔴 DESPESAS TOTAL | E2: ✅ SALDO LIVRE | G2: 📊 % SALDO / RECEITA
A3: =E33 -> 6904 | C3: =E23 -> 1696 | E3: =E33-E23 -> 5208 | G3: =IF(E33>0,(E33-E23)/E33,0) -> 0.75434531
A5: 🔴 DESPESAS — Nov/2025
A6: Data | B6: Descrição | C6: Parcela | D6: Tipo | E6: Valor (R$) | F6: Pago? | G6: Obs.
B7: GUARDA ROUPA | C7: 6 DE 12 | D7: PARCELADO | E7: 60 | G7: CARTAO IASMIM
B8: NEON IASMIM | E8: 458
A9: 11/25 | B9: Plano Cecília | D9: FIXO | E9: 250
A10: 11/25 | B10: Água / Esgoto | D10: FIXO | E10: 200
A12: 11/25 | B12: Celular TIM | D12: FIXO | E12: 140 | G12: RAFAH E GABRIELA
A13: 11/25 | B13: Plano NENA | D13: FIXO | E13: 288
A14: 11/25 | B14: Internet Casa | D14: FIXO | E14: 100
B16: CREDICARD | D16: FIXO | E16: 200
E18: 0
E19: 0
E20: 0
A21: Total Fixas/Parc. | E21: =SUM(E7:E18) -> 1696
A22: Despesas Gerais (est.)
A23: TOTAL DESPESAS MÊS | E23: =E21+E22 -> 1696
A25: 🟢 RECEITAS — Nov/2025
A26: Data | B26: Descrição | C26: Parcela | D26: Tipo | E26: Valor (R$) | F26: Recebido? | G26: Obs.
A27: 46327 | B27: Apartamento Rafa | C27: — | D27: Fixo | E27: 2870
A28: 46327 | B28: Salário Rafa | C28: — | D28: Fixo | E28: 2200
A30: 46327 | B30: 1° parcela decimo rafa | E30: 1400
A31: 46327 | B31: 1° parcela decimno gabriela | E31: 434
E32: 0
A33: TOTAL RECEITAS | E33: =SUM(E27:E32) -> 6904
A35: 💡 ANÁLISE RÁPIDA DO MÊS
A36: Saldo do mês: | E36: =E33-E23 -> 5208
A37: Aporte sugerido (20%): | E37: =0.7*(E33-E23) -> 3645.6
A38: Reserva de emergência: | E38: =E23/6 -> 282.66667

Sheet dez -26
A1: 💰 FINANÇAS — DEZ/2025
A2: 💰 RECEITA TOTAL | C2: 🔴 DESPESAS TOTAL | E2: ✅ SALDO LIVRE | G2: 📊 % SALDO / RECEITA
A3: =E33 -> 6914 | C3: =E23 -> 1848 | E3: =E33-E23 -> 5066 | G3: =IF(E33>0,(E33-E23)/E33,0) -> 0.73271623
A5: 🔴 DESPESAS — Dez/2025
A6: Data | B6: Descrição | C6: Parcela | D6: Tipo | E6: Valor (R$) | F6: Pago? | G6: Obs.
B7: GUARDA ROUPA | C7: 7 DE 12 | D7: PARCELADO | E7: 60 | G7: CARTAO IASMIM
A8: 12/25 | B8: NEON IASMIM | E8: 108
A9: 12/25 | B9: Plano Cecília | D9: FIXO | E9: 250
A10: 12/25 | B10: Água / Esgoto | D10: FIXO | E10: 178
A11: 12/25
A12: 12/25 | B12: Celular TIM | D12: FIXO | E12: 140 | G12: RAFAH E GABRIELA
A13: 12/25 | B13: Plano NENA | D13: FIXO | E13: 288
B14: Internet Casa | D14: FIXO | E14: 100
B15: CASA BAHIA | C15: 5 DE 5 | D15: PARCELADO 224 | E15: 224
B16: CREDICARD | D16: FIXO | E16: 200
B17: CURSO ELETRO TEC | C17: 3 DE 5 | D17: PARCELADO | E17: 300
E19: 0
E20: 0
A21: Total Fixas/Parc. | E21: =SUM(E7:E20) -> 1848
A22: Despesas Gerais (est.)
A23: TOTAL DESPESAS MÊS | E23: =E21+E22 -> 1848
A25: 🟢 RECEITAS — Dez/2025
A26: Data | B26: Descrição | C26: Parcela | D26: Tipo | E26: Valor (R$) | F26: Recebido? | G26: Obs.
A27: 46327 | B27: Apartamento Rafa | C27: — | D27: Fixo | E27: 2880
A28: 46327 | B28: Salário Rafae gabi | C28: — | D28: Fixo | E28: 2200
A30: 46327 | B30: 2° parcela decimo rafa | D30: decimo | E30: 1400
A31: 46327 | B31: 2° parcela decimno gabriela | D31: decimo | E31: 434
E32: 0
A33: TOTAL RECEITAS | E33: =SUM(E27:E32) -> 6914
A35: 💡 ANÁLISE RÁPIDA DO MÊS
A36: Saldo do mês: | E36: =E33-E23 -> 5066
A37: Aporte sugerido (20%): | E37: =0.7*(E33-E23) -> 3546.2
A38: Reserva de emergência: | E38: =E23/6 -> 308

Sheet Jan-27
A1: 💰 FINANÇAS — JAN/2026
A2: 💰 RECEITA TOTAL | C2: 🔴 DESPESAS TOTAL | E2: ✅ SALDO LIVRE | G2: 📊 % SALDO / RECEITA
A3: =E28 -> 5000 | C3: =E18 -> 1111 | E3: =E28-E18 -> 3889 | G3: =IF(E28>0,(E28-E18)/E28,0) -> 0.7778
A5: 🔴 DESPESAS — Jan/2026
A6: Data | B6: Descrição | C6: Parcela | D6: Tipo | E6: Valor (R$) | F6: Pago? | G6: Obs.
A7: 01/26 | B7: Neon Iasmim | C7: 7/8 | D7: Parcelado | E7: 108
A8: 01/26 | B8: Plano Cecília | D8: Fixo | E8: 240
A9: 01/26 | B9: Água / Esgoto | D9: Fixo | E9: 200
A11: 01/26 | B11: Celular TIM | D11: Fixo | E11: 140
A12: 01/26 | B12: Plano NENA | D12: Fixo | E12: 288
B13: Internet Casa | D13: Fixo | E13: 135
A16: Total Fixas/Parc. | E16: =SUM(E7:E15) -> 1111
A17: Despesas Gerais (est.) | E17: 0
A18: TOTAL DESPESAS MÊS | E18: =E16+E17 -> 1111
A20: 🟢 RECEITAS — Jan/2026
A21: Data | B21: Descrição | C21: Parcela | D21: Tipo | E21: Valor (R$) | F21: Recebido? | G21: Obs.
A22: 01/26 | B22: Apartamento Rafa | C22: — | D22: Fixo | E22: 2800
A23: 01/26 | B23: Salário Rafa | C23: — | D23: Fixo | E23: 2200
A24: 01/26
A28: TOTAL RECEITAS | E28: =SUM(E22:E27) -> 5000
A30: 💡 ANÁLISE RÁPIDA DO MÊS
A31: Saldo do mês: | E31: =E28-E18 -> 3889
A32: Aporte sugerido (20%): | E32: =0.7*(E28-E18) -> 2722.3
A33: Reserva de emergência: | E33: =E18/6 -> 185.16667

Sheet Fev-27
A1: 💰 FINANÇAS — FEV/2026
A2: 💰 RECEITA TOTAL | C2: 🔴 DESPESAS TOTAL | E2: ✅ SALDO LIVRE | G2: 📊 % SALDO / RECEITA
A3: =E29 -> 5000 | C3: =E19 -> 1084 | E3: =E29-E19 -> 3916 | G3: =IF(E29>0,(E29-E19)/E29,0) -> 0.7832
A5: 🔴 DESPESAS — Fev/2026
A6: Data | B6: Descrição | C6: Parcela | D6: Tipo | E6: Valor (R$) | F6: Pago? | G6: Obs.
A9: 46419 | B9: Plano Cecília | D9: Fixo | E9: 216
A10: 46419 | B10: Água / Esgoto | D10: Fixo | E10: 230
A11: 46419 | B11: Energia | D11: Fixo | E11: 95
A12: 46419 | B12: Celular TIM | D12: Fixo | E12: 120
A13: 46419 | B13: Plano NENA | D13: Fixo | E13: 288
A14: 46419 | B14: Internet Casa | D14: Fixo | E14: 135
A17: Total Fixas/Parc. | E17: =SUM(E7:E16) -> 1084
A18: Despesas Gerais (est.)
A19: TOTAL DESPESAS MÊS | E19: =E17+E18 -> 1084
A21: 🟢 RECEITAS — Fev/2026
A22: Data | B22: Descrição | C22: Parcela | D22: Tipo | E22: Valor (R$) | F22: Recebido? | G22: Obs.
A23: 02/26
A24: 02/26 | B24: adintamento rafa e gabi | C24: — | D24: Fixo | E24: 2800
A25: 02/26 | B25: salario rafa e gabi | C25: — | D25: Fixo | E25: 2200
A29: TOTAL RECEITAS | E29: =SUM(E23:E28) -> 5000
A31: 💡 ANÁLISE RÁPIDA DO MÊS
A32: Saldo do mês: | E32: =E29-E19 -> 3916
A33: Aporte sugerido (20%): | E33: =0.7*(E29-E19) -> 2741.2
A34: Reserva de emergência: | E34: =E19/6 -> 180.66667

Sheet Mar-27
A1: 💰 FINANÇAS — MAR/2026
A2: 💰 RECEITA TOTAL | C2: 🔴 DESPESAS TOTAL | E2: ✅ SALDO LIVRE | G2: 📊 % SALDO / RECEITA
A3: =E27 -> 5125 | C3: =E17 -> 1084 | E3: =E27-E17 -> 4041 | G3: =IF(E27>0,(E27-E17)/E27,0) -> 0.7884878
A5: 🔴 DESPESAS — Mar/2026
A6: Data | B6: Descrição | C6: Parcela | D6: Tipo | E6: Valor (R$) | F6: Pago? | G6: Obs.
A7: 03/26 | B7: Plano Cecília | D7: Fixo | E7: 216
A8: 03/26 | B8: Água / Esgoto | D8: Fixo | E8: 230
A9: 03/26 | B9: Energia | D9: Fixo | E9: 95
A10: 03/26 | B10: Celular TIM | D10: Fixo | E10: 120
A11: 03/26 | B11: Plano NENA | D11: Fixo | E11: 288
B12: Internet Casa | D12: Fixo | E12: 135
A15: Total Fixas/Parc. | E15: =SUM(E7:E14) -> 1084
A16: Despesas Gerais (est.)
A17: TOTAL DESPESAS MÊS | E17: =E15+E16 -> 1084
A19: 🟢 RECEITAS — Mar/2026
A20: Data | B20: Descrição | C20: Parcela | D20: Tipo | E20: Valor (R$) | F20: Recebido? | G20: Obs.
A21: 46447 | B21: Apartamento Rafa | C21: — | D21: Fixo | E21: 1475
A22: 46447 | B22: Salário Rafa | C22: — | D22: Fixo | E22: 1300
A23: 46447 | B23: Salário Gabi | C23: — | D23: Fixo | E23: 1500
A24: 46447 | B24: pis | E24: 850
A27: TOTAL RECEITAS | E27: =SUM(E21:E26) -> 5125
A29: 💡 ANÁLISE RÁPIDA DO MÊS
A30: Saldo do mês: | E30: =E27-E17 -> 4041
A31: Aporte sugerido (20%): | E31: =0.7*(E27-E17) -> 2828.7
A32: Reserva de emergência: | E32: =E17/6 -> 180.66667

Sheet Abr-27
A1: 💰 FINANÇAS — ABR/2026
A2: 💰 RECEITA TOTAL | C2: 🔴 DESPESAS TOTAL | E2: ✅ SALDO LIVRE | G2: 📊 % SALDO / RECEITA
A3: =E29 -> 4275 | C3: =E19 -> 3080 | E3: =E29-E19 -> 1195 | G3: =IF(E29>0,(E29-E19)/E29,0) -> 0.27953216
A5: 🔴 DESPESAS — Abr/2026
A6: Data | B6: Descrição | C6: Parcela | D6: Tipo | E6: Valor (R$) | F6: Pago? | G6: Obs.
A7: 04/26 | B7: Neon Fasomim | C7: Quitado | D7: Parcelado | E7: 86
A8: 04/26 | B8: Plano Cecília | D8: Fixo | E8: 216
A9: 04/26 | B9: Água / Esgoto | D9: Fixo | E9: 230
A10: 04/26 | B10: Energia | D10: Fixo | E10: 95
A11: 04/26 | B11: Celular TIM | D11: Fixo | E11: 120
A12: 04/26 | B12: Plano NENA | D12: Fixo | E12: 288
A13: 04/26 | B13: Internet Casa | D13: Fixo | E13: 135
A14: 04/27 | B14: Parcela Empréstimo LECCA | D14: Fixo | E14: ='💳 Empréstimo'!F18 -> 560 | G14: Parcela 7/36
A17: Total Fixas/Parc. | E17: =SUM(E7:E16) -> 1730
A18: Despesas Gerais (est.) | E18: 1350
A19: TOTAL DESPESAS MÊS | E19: =E17+E18 -> 3080
A21: 🟢 RECEITAS — Abr/2026
A22: Data | B22: Descrição | C22: Parcela | D22: Tipo | E22: Valor (R$) | F22: Recebido? | G22: Obs.
A23: 04/26 | B23: Apartamento Rafa | C23: — | D23: Fixo | E23: 1475
A24: 04/26 | B24: Salário Rafa | C24: — | D24: Fixo | E24: 1300
A25: 04/26 | B25: Salário Gabi | C25: — | D25: Fixo | E25: 1500
A29: TOTAL RECEITAS | E29: =SUM(E23:E28) -> 4275
A31: 💡 ANÁLISE RÁPIDA DO MÊS
A32: Saldo do mês: | E32: =E29-E19 -> 1195
A33: Aporte sugerido (20%): | E33: =0.7*(E29-E19) -> 836.5
A34: Reserva de emergência: | E34: =E19/6 -> 513.33333

Sheet Mai-27
A1: 💰 FINANÇAS — MAI/2026
A2: 💰 RECEITA TOTAL | C2: 🔴 DESPESAS TOTAL | E2: ✅ SALDO LIVRE | G2: 📊 % SALDO / RECEITA
A3: =E29 -> 4275 | C3: =E19 -> 3080 | E3: =E29-E19 -> 1195 | G3: =IF(E29>0,(E29-E19)/E29,0) -> 0.27953216
A5: 🔴 DESPESAS — Mai/2026
A6: Data | B6: Descrição | C6: Parcela | D6: Tipo | E6: Valor (R$) | F6: Pago? | G6: Obs.
A7: 05/26 | B7: Neon Fasomim | C7: Quitado | D7: Parcelado | E7: 86
A8: 05/26 | B8: Plano Cecília | D8: Fixo | E8: 216
A9: 05/26 | B9: Água / Esgoto | D9: Fixo | E9: 230
A10: 05/26 | B10: Energia | D10: Fixo | E10: 95
A11: 05/26 | B11: Celular TIM | D11: Fixo | E11: 120
A12: 05/26 | B12: Plano NENA | D12: Fixo | E12: 288
A13: 05/26 | B13: Internet Casa | D13: Fixo | E13: 135
A14: 05/27 | B14: Parcela Empréstimo LECCA | D14: Fixo | E14: ='💳 Empréstimo'!F19 -> 560 | G14: Parcela 8/36
A17: Total Fixas/Parc. | E17: =SUM(E7:E16) -> 1730
A18: Despesas Gerais (est.) | E18: 1350
A19: TOTAL DESPESAS MÊS | E19: =E17+E18 -> 3080
A21: 🟢 RECEITAS — Mai/2026
A22: Data | B22: Descrição | C22: Parcela | D22: Tipo | E22: Valor (R$) | F22: Recebido? | G22: Obs.
A23: 05/26 | B23: Apartamento Rafa | C23: — | D23: Fixo | E23: 1475
A24: 05/26 | B24: Salário Rafa | C24: — | D24: Fixo | E24: 1300
A25: 05/26 | B25: Salário Gabi | C25: — | D25: Fixo | E25: 1500
A29: TOTAL RECEITAS | E29: =SUM(E23:E28) -> 4275
A31: 💡 ANÁLISE RÁPIDA DO MÊS
A32: Saldo do mês: | E32: =E29-E19 -> 1195
A33: Aporte sugerido (20%): | E33: =0.7*(E29-E19) -> 836.5
A34: Reserva de emergência: | E34: =E19/6 -> 513.33333

Sheet Jun-27
A1: 💰 FINANÇAS — JUN/2026
A2: 💰 RECEITA TOTAL | C2: 🔴 DESPESAS TOTAL | E2: ✅ SALDO LIVRE | G2: 📊 % SALDO / RECEITA
A3: =E29 -> 4275 | C3: =E19 -> 3080 | E3: =E29-E19 -> 1195 | G3: =IF(E29>0,(E29-E19)/E29,0) -> 0.27953216
A5: 🔴 DESPESAS — Jun/2026
A6: Data | B6: Descrição | C6: Parcela | D6: Tipo | E6: Valor (R$) | F6: Pago? | G6: Obs.
A7: 06/26 | B7: Neon Fasomim | C7: Quitado | D7: Parcelado | E7: 86
A8: 06/26 | B8: Plano Cecília | D8: Fixo | E8: 216
A9: 06/26 | B9: Água / Esgoto | D9: Fixo | E9: 230
A10: 06/26 | B10: Energia | D10: Fixo | E10: 95
A11: 06/26 | B11: Celular TIM | D11: Fixo | E11: 120
A12: 06/26 | B12: Plano NENA | D12: Fixo | E12: 288
A13: 06/26 | B13: Internet Casa | D13: Fixo | E13: 135
A14: 06/27 | B14: Parcela Empréstimo LECCA | D14: Fixo | E14: ='💳 Empréstimo'!F20 -> 560 | G14: Parcela 9/36
A17: Total Fixas/Parc. | E17: =SUM(E7:E16) -> 1730
A18: Despesas Gerais (est.) | E18: 1350
A19: TOTAL DESPESAS MÊS | E19: =E17+E18 -> 3080
A21: 🟢 RECEITAS — Jun/2026
A22: Data | B22: Descrição | C22: Parcela | D22: Tipo | E22: Valor (R$) | F22: Recebido? | G22: Obs.
A23: 06/26 | B23: Apartamento Rafa | C23: — | D23: Fixo | E23: 1475
A24: 06/26 | B24: Salário Rafa | C24: — | D24: Fixo | E24: 1300
A25: 06/26 | B25: Salário Gabi | C25: — | D25: Fixo | E25: 1500
A29: TOTAL RECEITAS | E29: =SUM(E23:E28) -> 4275
A31: 💡 ANÁLISE RÁPIDA DO MÊS
A32: Saldo do mês: | E32: =E29-E19 -> 1195
A33: Aporte sugerido (20%): | E33: =0.7*(E29-E19) -> 836.5
A34: Reserva de emergência: | E34: =E19/6 -> 513.33333

Sheet Jul-27
A1: 💰 FINANÇAS — JUL/2027
A2: 💰 RECEITA TOTAL | C2: 🔴 DESPESAS TOTAL | E2: ✅ SALDO LIVRE | G2: 📊 % SALDO / RECEITA
A3: =E29 -> 4275 | C3: =E19 -> 3080 | E3: =E29-E19 -> 1195 | G3: =IF(E29>0,(E29-E19)/E29,0) -> 0.27953216
A5: 🔴 DESPESAS — Jul/2027
A6: Data | B6: Descrição | C6: Parcela | D6: Tipo | E6: Valor (R$) | F6: Pago? | G6: Obs.
A7: 07/27 | B7: Neon Fasomim | C7: Quitado | D7: Parcelado | E7: 86
A8: 07/27 | B8: Plano Cecília | D8: Fixo | E8: 216
A9: 07/27 | B9: Água / Esgoto | D9: Fixo | E9: 230
A10: 07/27 | B10: Energia | D10: Fixo | E10: 95
A11: 07/27 | B11: Celular TIM | D11: Fixo | E11: 120
A12: 07/27 | B12: Plano NENA | D12: Fixo | E12: 288
A13: 07/27 | B13: Internet Casa | D13: Fixo | E13: 135
A14: 07/27 | B14: Parcela Empréstimo LECCA | D14: Fixo | E14: ='💳 Empréstimo'!F21 -> 560 | G14: Parcela 10/36
A17: Total Fixas/Parc. | E17: =SUM(E7:E16) -> 1730
A18: Despesas Gerais (est.) | E18: 1350
A19: TOTAL DESPESAS MÊS | E19: =E17+E18 -> 3080
A21: 🟢 RECEITAS — Jul/2027
A22: Data | B22: Descrição | C22: Parcela | D22: Tipo | E22: Valor (R$) | F22: Recebido? | G22: Obs.
A23: 07/27 | B23: Apartamento Rafa | C23: — | D23: Fixo | E23: 1475
A24: 07/27 | B24: Salário Rafa | C24: — | D24: Fixo | E24: 1300
A25: 07/27 | B25: Salário Gabi | C25: — | D25: Fixo | E25: 1500
A29: TOTAL RECEITAS | E29: =SUM(E23:E28) -> 4275
A31: 💡 ANÁLISE RÁPIDA DO MÊS
A32: Saldo do mês: | E32: =E29-E19 -> 1195
A33: Aporte sugerido (20%): | E33: =0.7*(E29-E19) -> 836.5
A34: Reserva de emergência: | E34: =E19/6 -> 513.33333

Sheet Ago-27
A1: 💰 FINANÇAS — AGO/2027
A2: 💰 RECEITA TOTAL | C2: 🔴 DESPESAS TOTAL | E2: ✅ SALDO LIVRE | G2: 📊 % SALDO / RECEITA
A3: =E29 -> 4275 | C3: =E19 -> 3080 | E3: =E29-E19 -> 1195 | G3: =IF(E29>0,(E29-E19)/E29,0) -> 0.27953216
A5: 🔴 DESPESAS — Ago/2027
A6: Data | B6: Descrição | C6: Parcela | D6: Tipo | E6: Valor (R$) | F6: Pago? | G6: Obs.
A7: 08/27 | B7: Neon Fasomim | C7: Quitado | D7: Parcelado | E7: 86
A8: 08/27 | B8: Plano Cecília | D8: Fixo | E8: 216
A9: 08/27 | B9: Água / Esgoto | D9: Fixo | E9: 230
A10: 08/27 | B10: Energia | D10: Fixo | E10: 95
A11: 08/27 | B11: Celular TIM | D11: Fixo | E11: 120
A12: 08/27 | B12: Plano NENA | D12: Fixo | E12: 288
A13: 08/27 | B13: Internet Casa | D13: Fixo | E13: 135
A14: 08/27 | B14: Parcela Empréstimo LECCA | D14: Fixo | E14: ='💳 Empréstimo'!F22 -> 560 | G14: Parcela 11/36
A17: Total Fixas/Parc. | E17: =SUM(E7:E16) -> 1730
A18: Despesas Gerais (est.) | E18: 1350
A19: TOTAL DESPESAS MÊS | E19: =E17+E18 -> 3080
A21: 🟢 RECEITAS — Ago/2027
A22: Data | B22: Descrição | C22: Parcela | D22: Tipo | E22: Valor (R$) | F22: Recebido? | G22: Obs.
A23: 08/27 | B23: Apartamento Rafa | C23: — | D23: Fixo | E23: 1475
A24: 08/27 | B24: Salário Rafa | C24: — | D24: Fixo | E24: 1300
A25: 08/27 | B25: Salário Gabi | C25: — | D25: Fixo | E25: 1500
A29: TOTAL RECEITAS | E29: =SUM(E23:E28) -> 4275
A31: 💡 ANÁLISE RÁPIDA DO MÊS
A32: Saldo do mês: | E32: =E29-E19 -> 1195
A33: Aporte sugerido (20%): | E33: =0.7*(E29-E19) -> 836.5
A34: Reserva de emergência: | E34: =E19/6 -> 513.33333

Sheet Set-27
A1: 💰 FINANÇAS — SET/2027
A2: 💰 RECEITA TOTAL | C2: 🔴 DESPESAS TOTAL | E2: ✅ SALDO LIVRE | G2: 📊 % SALDO / RECEITA
A3: =E29 -> 4275 | C3: =E19 -> 3080 | E3: =E29-E19 -> 1195 | G3: =IF(E29>0,(E29-E19)/E29,0) -> 0.27953216
A5: 🔴 DESPESAS — Set/2027
A6: Data | B6: Descrição | C6: Parcela | D6: Tipo | E6: Valor (R$) | F6: Pago? | G6: Obs.
A7: 09/27 | B7: Neon Fasomim | C7: Quitado | D7: Parcelado | E7: 86
A8: 09/27 | B8: Plano Cecília | D8: Fixo | E8: 216
A9: 09/27 | B9: Água / Esgoto | D9: Fixo | E9: 230
A10: 09/27 | B10: Energia | D10: Fixo | E10: 95
A11: 09/27 | B11: Celular TIM | D11: Fixo | E11: 120
A12: 09/27 | B12: Plano NENA | D12: Fixo | E12: 288
A13: 09/27 | B13: Internet Casa | D13: Fixo | E13: 135
A14: 09/27 | B14: Parcela Empréstimo LECCA | D14: Fixo | E14: ='💳 Empréstimo'!F23 -> 560 | G14: Parcela 12/36
A17: Total Fixas/Parc. | E17: =SUM(E7:E16) -> 1730
A18: Despesas Gerais (est.) | E18: 1350
A19: TOTAL DESPESAS MÊS | E19: =E17+E18 -> 3080
A21: 🟢 RECEITAS — Set/2027
A22: Data | B22: Descrição | C22: Parcela | D22: Tipo | E22: Valor (R$) | F22: Recebido? | G22: Obs.
A23: 09/27 | B23: Apartamento Rafa | C23: — | D23: Fixo | E23: 1475
A24: 09/27 | B24: Salário Rafa | C24: — | D24: Fixo | E24: 1300
A25: 09/27 | B25: Salário Gabi | C25: — | D25: Fixo | E25: 1500
A29: TOTAL RECEITAS | E29: =SUM(E23:E28) -> 4275
A31: 💡 ANÁLISE RÁPIDA DO MÊS
A32: Saldo do mês: | E32: =E29-E19 -> 1195
A33: Aporte sugerido (20%): | E33: =0.7*(E29-E19) -> 836.5
A34: Reserva de emergência: | E34: =E19/6 -> 513.33333

Sheet Out-27
A1: 💰 FINANÇAS — OUT/2027
A2: 💰 RECEITA TOTAL | C2: 🔴 DESPESAS TOTAL | E2: ✅ SALDO LIVRE | G2: 📊 % SALDO / RECEITA
A3: =E29 -> 4275 | C3: =E19 -> 3080 | E3: =E29-E19 -> 1195 | G3: =IF(E29>0,(E29-E19)/E29,0) -> 0.27953216
A5: 🔴 DESPESAS — Out/2027
A6: Data | B6: Descrição | C6: Parcela | D6: Tipo | E6: Valor (R$) | F6: Pago? | G6: Obs.
A7: 10/27 | B7: Neon Fasomim | C7: Quitado | D7: Parcelado | E7: 86
A8: 10/27 | B8: Plano Cecília | D8: Fixo | E8: 216
A9: 10/27 | B9: Água / Esgoto | D9: Fixo | E9: 230
A10: 10/27 | B10: Energia | D10: Fixo | E10: 95
A11: 10/27 | B11: Celular TIM | D11: Fixo | E11: 120
A12: 10/27 | B12: Plano NENA | D12: Fixo | E12: 288
A13: 10/27 | B13: Internet Casa | D13: Fixo | E13: 135
A14: 10/27 | B14: Parcela Empréstimo LECCA | D14: Fixo | E14: ='💳 Empréstimo'!F24 -> 560 | G14: Parcela 13/36
A17: Total Fixas/Parc. | E17: =SUM(E7:E16) -> 1730
A18: Despesas Gerais (est.) | E18: 1350
A19: TOTAL DESPESAS MÊS | E19: =E17+E18 -> 3080
A21: 🟢 RECEITAS — Out/2027
A22: Data | B22: Descrição | C22: Parcela | D22: Tipo | E22: Valor (R$) | F22: Recebido? | G22: Obs.
A23: 10/27 | B23: Apartamento Rafa | C23: — | D23: Fixo | E23: 1475
A24: 10/27 | B24: Salário Rafa | C24: — | D24: Fixo | E24: 1300
A25: 10/27 | B25: Salário Gabi | C25: — | D25: Fixo | E25: 1500
A29: TOTAL RECEITAS | E29: =SUM(E23:E28) -> 4275
A31: 💡 ANÁLISE RÁPIDA DO MÊS
A32: Saldo do mês: | E32: =E29-E19 -> 1195
A33: Aporte sugerido (20%): | E33: =0.7*(E29-E19) -> 836.5
A34: Reserva de emergência: | E34: =E19/6 -> 513.33333

Sheet Nov-27
A1: 💰 FINANÇAS — NOV/2027
A2: 💰 RECEITA TOTAL | C2: 🔴 DESPESAS TOTAL | E2: ✅ SALDO LIVRE | G2: 📊 % SALDO / RECEITA
A3: =E29 -> 4275 | C3: =E19 -> 3080 | E3: =E29-E19 -> 1195 | G3: =IF(E29>0,(E29-E19)/E29,0) -> 0.27953216
A5: 🔴 DESPESAS — Nov/2027
A6: Data | B6: Descrição | C6: Parcela | D6: Tipo | E6: Valor (R$) | F6: Pago? | G6: Obs.
A7: 11/27 | B7: Neon Fasomim | C7: Quitado | D7: Parcelado | E7: 86
A8: 11/27 | B8: Plano Cecília | D8: Fixo | E8: 216
A9: 11/27 | B9: Água / Esgoto | D9: Fixo | E9: 230
A10: 11/27 | B10: Energia | D10: Fixo | E10: 95
A11: 11/27 | B11: Celular TIM | D11: Fixo | E11: 120
A12: 11/27 | B12: Plano NENA | D12: Fixo | E12: 288
A13: 11/27 | B13: Internet Casa | D13: Fixo | E13: 135
A14: 11/27 | B14: Parcela Empréstimo LECCA | D14: Fixo | E14: ='💳 Empréstimo'!F25 -> 560 | G14: Parcela 14/36
A17: Total Fixas/Parc. | E17: =SUM(E7:E16) -> 1730
A18: Despesas Gerais (est.) | E18: 1350
A19: TOTAL DESPESAS MÊS | E19: =E17+E18 -> 3080
A21: 🟢 RECEITAS — Nov/2027
A22: Data | B22: Descrição | C22: Parcela | D22: Tipo | E22: Valor (R$) | F22: Recebido? | G22: Obs.
A23: 11/27 | B23: Apartamento Rafa | C23: — | D23: Fixo | E23: 1475
A24: 11/27 | B24: Salário Rafa | C24: — | D24: Fixo | E24: 1300
A25: 11/27 | B25: Salário Gabi | C25: — | D25: Fixo | E25: 1500
A29: TOTAL RECEITAS | E29: =SUM(E23:E28) -> 4275
A31: 💡 ANÁLISE RÁPIDA DO MÊS
A32: Saldo do mês: | E32: =E29-E19 -> 1195
A33: Aporte sugerido (20%): | E33: =0.7*(E29-E19) -> 836.5
A34: Reserva de emergência: | E34: =E19/6 -> 513.33333

Sheet Dez-27
A1: 💰 FINANÇAS — DEZ/2027
A2: 💰 RECEITA TOTAL | C2: 🔴 DESPESAS TOTAL | E2: ✅ SALDO LIVRE | G2: 📊 % SALDO / RECEITA
A3: =E29 -> 4275 | C3: =E19 -> 3080 | E3: =E29-E19 -> 1195 | G3: =IF(E29>0,(E29-E19)/E29,0) -> 0.27953216
A5: 🔴 DESPESAS — Dez/2027
A6: Data | B6: Descrição | C6: Parcela | D6: Tipo | E6: Valor (R$) | F6: Pago? | G6: Obs.
A7: 12/27 | B7: Neon Fasomim | C7: Quitado | D7: Parcelado | E7: 86
A8: 12/27 | B8: Plano Cecília | D8: Fixo | E8: 216
A9: 12/27 | B9: Água / Esgoto | D9: Fixo | E9: 230
A10: 12/27 | B10: Energia | D10: Fixo | E10: 95
A11: 12/27 | B11: Celular TIM | D11: Fixo | E11: 120
A12: 12/27 | B12: Plano NENA | D12: Fixo | E12: 288
A13: 12/27 | B13: Internet Casa | D13: Fixo | E13: 135
A14: 12/27 | B14: Parcela Empréstimo LECCA | D14: Fixo | E14: ='💳 Empréstimo'!F26 -> 560 | G14: Parcela 15/36
A17: Total Fixas/Parc. | E17: =SUM(E7:E16) -> 1730
A18: Despesas Gerais (est.) | E18: 1350
A19: TOTAL DESPESAS MÊS | E19: =E17+E18 -> 3080
A21: 🟢 RECEITAS — Dez/2027
A22: Data | B22: Descrição | C22: Parcela | D22: Tipo | E22: Valor (R$) | F22: Recebido? | G22: Obs.
A23: 12/27 | B23: Apartamento Rafa | C23: — | D23: Fixo | E23: 1475
A24: 12/27 | B24: Salário Rafa | C24: — | D24: Fixo | E24: 1300
A25: 12/27 | B25: Salário Gabi | C25: — | D25: Fixo | E25: 1500
A29: TOTAL RECEITAS | E29: =SUM(E23:E28) -> 4275
A31: 💡 ANÁLISE RÁPIDA DO MÊS
A32: Saldo do mês: | E32: =E29-E19 -> 1195
A33: Aporte sugerido (20%): | E33: =0.7*(E29-E19) -> 836.5
A34: Reserva de emergência: | E34: =E19/6 -> 513.33333

Sheet Jan-28
A1: 💰 FINANÇAS — JAN/2028
A2: 💰 RECEITA TOTAL | C2: 🔴 DESPESAS TOTAL | E2: ✅ SALDO LIVRE | G2: 📊 % SALDO / RECEITA
A3: =E29 -> 4275 | C3: =E19 -> 3080 | E3: =E29-E19 -> 1195 | G3: =IF(E29>0,(E29-E19)/E29,0) -> 0.27953216
A5: 🔴 DESPESAS — Jan/2028
A6: Data | B6: Descrição | C6: Parcela | D6: Tipo | E6: Valor (R$) | F6: Pago? | G6: Obs.
A7: 01/28 | B7: Neon Fasomim | C7: Quitado | D7: Parcelado | E7: 86
A8: 01/28 | B8: Plano Cecília | D8: Fixo | E8: 216
A9: 01/28 | B9: Água / Esgoto | D9: Fixo | E9: 230
A10: 01/28 | B10: Energia | D10: Fixo | E10: 95
A11: 01/28 | B11: Celular TIM | D11: Fixo | E11: 120
A12: 01/28 | B12: Plano NENA | D12: Fixo | E12: 288
A13: 01/28 | B13: Internet Casa | D13: Fixo | E13: 135
A14: 01/28 | B14: Parcela Empréstimo LECCA | D14: Fixo | E14: ='💳 Empréstimo'!F27 -> 560 | G14: Parcela 16/36
A17: Total Fixas/Parc. | E17: =SUM(E7:E16) -> 1730
A18: Despesas Gerais (est.) | E18: 1350
A19: TOTAL DESPESAS MÊS | E19: =E17+E18 -> 3080
A21: 🟢 RECEITAS — Jan/2028
A22: Data | B22: Descrição | C22: Parcela | D22: Tipo | E22: Valor (R$) | F22: Recebido? | G22: Obs.
A23: 01/28 | B23: Apartamento Rafa | C23: — | D23: Fixo | E23: 1475
A24: 01/28 | B24: Salário Rafa | C24: — | D24: Fixo | E24: 1300
A25: 01/28 | B25: Salário Gabi | C25: — | D25: Fixo | E25: 1500
A29: TOTAL RECEITAS | E29: =SUM(E23:E28) -> 4275
A31: 💡 ANÁLISE RÁPIDA DO MÊS
A32: Saldo do mês: | E32: =E29-E19 -> 1195
A33: Aporte sugerido (20%): | E33: =0.7*(E29-E19) -> 836.5
A34: Reserva de emergência: | E34: =E19/6 -> 513.33333

Sheet Fev-28
A1: 💰 FINANÇAS — FEV/2028
A2: 💰 RECEITA TOTAL | C2: 🔴 DESPESAS TOTAL | E2: ✅ SALDO LIVRE | G2: 📊 % SALDO / RECEITA
A3: =E29 -> 4275 | C3: =E19 -> 3080 | E3: =E29-E19 -> 1195 | G3: =IF(E29>0,(E29-E19)/E29,0) -> 0.27953216
A5: 🔴 DESPESAS — Fev/2028
A6: Data | B6: Descrição | C6: Parcela | D6: Tipo | E6: Valor (R$) | F6: Pago? | G6: Obs.
A7: 02/28 | B7: Neon Fasomim | C7: Quitado | D7: Parcelado | E7: 86
A8: 02/28 | B8: Plano Cecília | D8: Fixo | E8: 216
A9: 02/28 | B9: Água / Esgoto | D9: Fixo | E9: 230
A10: 02/28 | B10: Energia | D10: Fixo | E10: 95
A11: 02/28 | B11: Celular TIM | D11: Fixo | E11: 120
A12: 02/28 | B12: Plano NENA | D12: Fixo | E12: 288
A13: 02/28 | B13: Internet Casa | D13: Fixo | E13: 135
A14: 02/28 | B14: Parcela Empréstimo LECCA | D14: Fixo | E14: ='💳 Empréstimo'!F28 -> 560 | G14: Parcela 17/36
A17: Total Fixas/Parc. | E17: =SUM(E7:E16) -> 1730
A18: Despesas Gerais (est.) | E18: 1350
A19: TOTAL DESPESAS MÊS | E19: =E17+E18 -> 3080
A21: 🟢 RECEITAS — Fev/2028
A22: Data | B22: Descrição | C22: Parcela | D22: Tipo | E22: Valor (R$) | F22: Recebido? | G22: Obs.
A23: 02/28 | B23: Apartamento Rafa | C23: — | D23: Fixo | E23: 1475
A24: 02/28 | B24: Salário Rafa | C24: — | D24: Fixo | E24: 1300
A25: 02/28 | B25: Salário Gabi | C25: — | D25: Fixo | E25: 1500
A29: TOTAL RECEITAS | E29: =SUM(E23:E28) -> 4275
A31: 💡 ANÁLISE RÁPIDA DO MÊS
A32: Saldo do mês: | E32: =E29-E19 -> 1195
A33: Aporte sugerido (20%): | E33: =0.7*(E29-E19) -> 836.5
A34: Reserva de emergência: | E34: =E19/6 -> 513.33333

Sheet Mar-28
A1: 💰 FINANÇAS — MAR/2028
A2: 💰 RECEITA TOTAL | C2: 🔴 DESPESAS TOTAL | E2: ✅ SALDO LIVRE | G2: 📊 % SALDO / RECEITA
A3: =E29 -> 4275 | C3: =E19 -> 3080 | E3: =E29-E19 -> 1195 | G3: =IF(E29>0,(E29-E19)/E29,0) -> 0.27953216
A5: 🔴 DESPESAS — Mar/2028
A6: Data | B6: Descrição | C6: Parcela | D6: Tipo | E6: Valor (R$) | F6: Pago? | G6: Obs.
A7: 03/28 | B7: Neon Fasomim | C7: Quitado | D7: Parcelado | E7: 86
A8: 03/28 | B8: Plano Cecília | D8: Fixo | E8: 216
A9: 03/28 | B9: Água / Esgoto | D9: Fixo | E9: 230
A10: 03/28 | B10: Energia | D10: Fixo | E10: 95
A11: 03/28 | B11: Celular TIM | D11: Fixo | E11: 120
A12: 03/28 | B12: Plano NENA | D12: Fixo | E12: 288
A13: 03/28 | B13: Internet Casa | D13: Fixo | E13: 135
A14: 03/28 | B14: Parcela Empréstimo LECCA | D14: Fixo | E14: ='💳 Empréstimo'!F29 -> 560 | G14: Parcela 18/36
A17: Total Fixas/Parc. | E17: =SUM(E7:E16) -> 1730
A18: Despesas Gerais (est.) | E18: 1350
A19: TOTAL DESPESAS MÊS | E19: =E17+E18 -> 3080
A21: 🟢 RECEITAS — Mar/2028
A22: Data | B22: Descrição | C22: Parcela | D22: Tipo | E22: Valor (R$) | F22: Recebido? | G22: Obs.
A23: 03/28 | B23: Apartamento Rafa | C23: — | D23: Fixo | E23: 1475
A24: 03/28 | B24: Salário Rafa | C24: — | D24: Fixo | E24: 1300
A25: 03/28 | B25: Salário Gabi | C25: — | D25: Fixo | E25: 1500
A29: TOTAL RECEITAS | E29: =SUM(E23:E28) -> 4275
A31: 💡 ANÁLISE RÁPIDA DO MÊS
A32: Saldo do mês: | E32: =E29-E19 -> 1195
A33: Aporte sugerido (20%): | E33: =0.7*(E29-E19) -> 836.5
A34: Reserva de emergência: | E34: =E19/6 -> 513.33333

Sheet Abr-28
A1: 💰 FINANÇAS — ABR/2028
A2: 💰 RECEITA TOTAL | C2: 🔴 DESPESAS TOTAL | E2: ✅ SALDO LIVRE | G2: 📊 % SALDO / RECEITA
A3: =E29 -> 4275 | C3: =E19 -> 3080 | E3: =E29-E19 -> 1195 | G3: =IF(E29>0,(E29-E19)/E29,0) -> 0.27953216
A5: 🔴 DESPESAS — Abr/2028
A6: Data | B6: Descrição | C6: Parcela | D6: Tipo | E6: Valor (R$) | F6: Pago? | G6: Obs.
A7: 04/28 | B7: Neon Fasomim | C7: Quitado | D7: Parcelado | E7: 86
A8: 04/28 | B8: Plano Cecília | D8: Fixo | E8: 216
A9: 04/28 | B9: Água / Esgoto | D9: Fixo | E9: 230
A10: 04/28 | B10: Energia | D10: Fixo | E10: 95
A11: 04/28 | B11: Celular TIM | D11: Fixo | E11: 120
A12: 04/28 | B12: Plano NENA | D12: Fixo | E12: 288
A13: 04/28 | B13: Internet Casa | D13: Fixo | E13: 135
A14: 04/28 | B14: Parcela Empréstimo LECCA | D14: Fixo | E14: ='💳 Empréstimo'!F30 -> 560 | G14: Parcela 19/36
A17: Total Fixas/Parc. | E17: =SUM(E7:E16) -> 1730
A18: Despesas Gerais (est.) | E18: 1350
A19: TOTAL DESPESAS MÊS | E19: =E17+E18 -> 3080
A21: 🟢 RECEITAS — Abr/2028
A22: Data | B22: Descrição | C22: Parcela | D22: Tipo | E22: Valor (R$) | F22: Recebido? | G22: Obs.
A23: 04/28 | B23: Apartamento Rafa | C23: — | D23: Fixo | E23: 1475
A24: 04/28 | B24: Salário Rafa | C24: — | D24: Fixo | E24: 1300
A25: 04/28 | B25: Salário Gabi | C25: — | D25: Fixo | E25: 1500
A29: TOTAL RECEITAS | E29: =SUM(E23:E28) -> 4275
A31: 💡 ANÁLISE RÁPIDA DO MÊS
A32: Saldo do mês: | E32: =E29-E19 -> 1195
A33: Aporte sugerido (20%): | E33: =0.7*(E29-E19) -> 836.5
A34: Reserva de emergência: | E34: =E19/6 -> 513.33333

Sheet Mai-28
A1: 💰 FINANÇAS — MAI/2028
A2: 💰 RECEITA TOTAL | C2: 🔴 DESPESAS TOTAL | E2: ✅ SALDO LIVRE | G2: 📊 % SALDO / RECEITA
A3: =E29 -> 4275 | C3: =E19 -> 3080 | E3: =E29-E19 -> 1195 | G3: =IF(E29>0,(E29-E19)/E29,0) -> 0.27953216
A5: 🔴 DESPESAS — Mai/2028
A6: Data | B6: Descrição | C6: Parcela | D6: Tipo | E6: Valor (R$) | F6: Pago? | G6: Obs.
A7: 05/28 | B7: Neon Fasomim | C7: Quitado | D7: Parcelado | E7: 86
A8: 05/28 | B8: Plano Cecília | D8: Fixo | E8: 216
A9: 05/28 | B9: Água / Esgoto | D9: Fixo | E9: 230
A10: 05/28 | B10: Energia | D10: Fixo | E10: 95
A11: 05/28 | B11: Celular TIM | D11: Fixo | E11: 120
A12: 05/28 | B12: Plano NENA | D12: Fixo | E12: 288
A13: 05/28 | B13: Internet Casa | D13: Fixo | E13: 135
A14: 05/28 | B14: Parcela Empréstimo LECCA | D14: Fixo | E14: ='💳 Empréstimo'!F31 -> 560 | G14: Parcela 20/36
A17: Total Fixas/Parc. | E17: =SUM(E7:E16) -> 1730
A18: Despesas Gerais (est.) | E18: 1350
A19: TOTAL DESPESAS MÊS | E19: =E17+E18 -> 3080
A21: 🟢 RECEITAS — Mai/2028
A22: Data | B22: Descrição | C22: Parcela | D22: Tipo | E22: Valor (R$) | F22: Recebido? | G22: Obs.
A23: 05/28 | B23: Apartamento Rafa | C23: — | D23: Fixo | E23: 1475
A24: 05/28 | B24: Salário Rafa | C24: — | D24: Fixo | E24: 1300
A25: 05/28 | B25: Salário Gabi | C25: — | D25: Fixo | E25: 1500
A29: TOTAL RECEITAS | E29: =SUM(E23:E28) -> 4275
A31: 💡 ANÁLISE RÁPIDA DO MÊS
A32: Saldo do mês: | E32: =E29-E19 -> 1195
A33: Aporte sugerido (20%): | E33: =0.7*(E29-E19) -> 836.5
A34: Reserva de emergência: | E34: =E19/6 -> 513.33333

Sheet Jun-28
A1: 💰 FINANÇAS — JUN/2028
A2: 💰 RECEITA TOTAL | C2: 🔴 DESPESAS TOTAL | E2: ✅ SALDO LIVRE | G2: 📊 % SALDO / RECEITA
A3: =E29 -> 4275 | C3: =E19 -> 3080 | E3: =E29-E19 -> 1195 | G3: =IF(E29>0,(E29-E19)/E29,0) -> 0.27953216
A5: 🔴 DESPESAS — Jun/2028
A6: Data | B6: Descrição | C6: Parcela | D6: Tipo | E6: Valor (R$) | F6: Pago? | G6: Obs.
A7: 06/28 | B7: Neon Fasomim | C7: Quitado | D7: Parcelado | E7: 86
A8: 06/28 | B8: Plano Cecília | D8: Fixo | E8: 216
A9: 06/28 | B9: Água / Esgoto | D9: Fixo | E9: 230
A10: 06/28 | B10: Energia | D10: Fixo | E10: 95
A11: 06/28 | B11: Celular TIM | D11: Fixo | E11: 120
A12: 06/28 | B12: Plano NENA | D12: Fixo | E12: 288
A13: 06/28 | B13: Internet Casa | D13: Fixo | E13: 135
A14: 06/28 | B14: Parcela Empréstimo LECCA | D14: Fixo | E14: ='💳 Empréstimo'!F32 -> 560 | G14: Parcela 21/36
A17: Total Fixas/Parc. | E17: =SUM(E7:E16) -> 1730
A18: Despesas Gerais (est.) | E18: 1350
A19: TOTAL DESPESAS MÊS | E19: =E17+E18 -> 3080
A21: 🟢 RECEITAS — Jun/2028
A22: Data | B22: Descrição | C22: Parcela | D22: Tipo | E22: Valor (R$) | F22: Recebido? | G22: Obs.
A23: 06/28 | B23: Apartamento Rafa | C23: — | D23: Fixo | E23: 1475
A24: 06/28 | B24: Salário Rafa | C24: — | D24: Fixo | E24: 1300
A25: 06/28 | B25: Salário Gabi | C25: — | D25: Fixo | E25: 1500
A29: TOTAL RECEITAS | E29: =SUM(E23:E28) -> 4275
A31: 💡 ANÁLISE RÁPIDA DO MÊS
A32: Saldo do mês: | E32: =E29-E19 -> 1195
A33: Aporte sugerido (20%): | E33: =0.7*(E29-E19) -> 836.5
A34: Reserva de emergência: | E34: =E19/6 -> 513.33333

Sheet Jul-28
A1: 💰 FINANÇAS — JUL/2028
A2: 💰 RECEITA TOTAL | C2: 🔴 DESPESAS TOTAL | E2: ✅ SALDO LIVRE | G2: 📊 % SALDO / RECEITA
A3: =E29 -> 4275 | C3: =E19 -> 3080 | E3: =E29-E19 -> 1195 | G3: =IF(E29>0,(E29-E19)/E29,0) -> 0.27953216
A5: 🔴 DESPESAS — Jul/2028
A6: Data | B6: Descrição | C6: Parcela | D6: Tipo | E6: Valor (R$) | F6: Pago? | G6: Obs.
A7: 07/28 | B7: Neon Fasomim | C7: Quitado | D7: Parcelado | E7: 86
A8: 07/28 | B8: Plano Cecília | D8: Fixo | E8: 216
A9: 07/28 | B9: Água / Esgoto | D9: Fixo | E9: 230
A10: 07/28 | B10: Energia | D10: Fixo | E10: 95
A11: 07/28 | B11: Celular TIM | D11: Fixo | E11: 120
A12: 07/28 | B12: Plano NENA | D12: Fixo | E12: 288
A13: 07/28 | B13: Internet Casa | D13: Fixo | E13: 135
A14: 07/28 | B14: Parcela Empréstimo LECCA | D14: Fixo | E14: ='💳 Empréstimo'!F33 -> 560 | G14: Parcela 22/36
A17: Total Fixas/Parc. | E17: =SUM(E7:E16) -> 1730
A18: Despesas Gerais (est.) | E18: 1350
A19: TOTAL DESPESAS MÊS | E19: =E17+E18 -> 3080
A21: 🟢 RECEITAS — Jul/2028
A22: Data | B22: Descrição | C22: Parcela | D22: Tipo | E22: Valor (R$) | F22: Recebido? | G22: Obs.
A23: 07/28 | B23: Apartamento Rafa | C23: — | D23: Fixo | E23: 1475
A24: 07/28 | B24: Salário Rafa | C24: — | D24: Fixo | E24: 1300
A25: 07/28 | B25: Salário Gabi | C25: — | D25: Fixo | E25: 1500
A29: TOTAL RECEITAS | E29: =SUM(E23:E28) -> 4275
A31: 💡 ANÁLISE RÁPIDA DO MÊS
A32: Saldo do mês: | E32: =E29-E19 -> 1195
A33: Aporte sugerido (20%): | E33: =0.7*(E29-E19) -> 836.5
A34: Reserva de emergência: | E34: =E19/6 -> 513.33333

Sheet Ago-28
A1: 💰 FINANÇAS — AGO/2028
A2: 💰 RECEITA TOTAL | C2: 🔴 DESPESAS TOTAL | E2: ✅ SALDO LIVRE | G2: 📊 % SALDO / RECEITA
A3: =E29 -> 4275 | C3: =E19 -> 3080 | E3: =E29-E19 -> 1195 | G3: =IF(E29>0,(E29-E19)/E29,0) -> 0.27953216
A5: 🔴 DESPESAS — Ago/2028
A6: Data | B6: Descrição | C6: Parcela | D6: Tipo | E6: Valor (R$) | F6: Pago? | G6: Obs.
A7: 08/28 | B7: Neon Fasomim | C7: Quitado | D7: Parcelado | E7: 86
A8: 08/28 | B8: Plano Cecília | D8: Fixo | E8: 216
A9: 08/28 | B9: Água / Esgoto | D9: Fixo | E9: 230
A10: 08/28 | B10: Energia | D10: Fixo | E10: 95
A11: 08/28 | B11: Celular TIM | D11: Fixo | E11: 120
A12: 08/28 | B12: Plano NENA | D12: Fixo | E12: 288
A13: 08/28 | B13: Internet Casa | D13: Fixo | E13: 135
A14: 08/28 | B14: Parcela Empréstimo LECCA | D14: Fixo | E14: ='💳 Empréstimo'!F34 -> 560 | G14: Parcela 23/36
A17: Total Fixas/Parc. | E17: =SUM(E7:E16) -> 1730
A18: Despesas Gerais (est.) | E18: 1350
A19: TOTAL DESPESAS MÊS | E19: =E17+E18 -> 3080
A21: 🟢 RECEITAS — Ago/2028
A22: Data | B22: Descrição | C22: Parcela | D22: Tipo | E22: Valor (R$) | F22: Recebido? | G22: Obs.
A23: 08/28 | B23: Apartamento Rafa | C23: — | D23: Fixo | E23: 1475
A24: 08/28 | B24: Salário Rafa | C24: — | D24: Fixo | E24: 1300
A25: 08/28 | B25: Salário Gabi | C25: — | D25: Fixo | E25: 1500
A29: TOTAL RECEITAS | E29: =SUM(E23:E28) -> 4275
A31: 💡 ANÁLISE RÁPIDA DO MÊS
A32: Saldo do mês: | E32: =E29-E19 -> 1195
A33: Aporte sugerido (20%): | E33: =0.7*(E29-E19) -> 836.5
A34: Reserva de emergência: | E34: =E19/6 -> 513.33333

Sheet Set-28
A1: 💰 FINANÇAS — SET/2028
A2: 💰 RECEITA TOTAL | C2: 🔴 DESPESAS TOTAL | E2: ✅ SALDO LIVRE | G2: 📊 % SALDO / RECEITA
A3: =E29 -> 4275 | C3: =E19 -> 3080 | E3: =E29-E19 -> 1195 | G3: =IF(E29>0,(E29-E19)/E29,0) -> 0.27953216
A5: 🔴 DESPESAS — Set/2028
A6: Data | B6: Descrição | C6: Parcela | D6: Tipo | E6: Valor (R$) | F6: Pago? | G6: Obs.
A7: 09/28 | B7: Neon Fasomim | C7: Quitado | D7: Parcelado | E7: 86
A8: 09/28 | B8: Plano Cecília | D8: Fixo | E8: 216
A9: 09/28 | B9: Água / Esgoto | D9: Fixo | E9: 230
A10: 09/28 | B10: Energia | D10: Fixo | E10: 95
A11: 09/28 | B11: Celular TIM | D11: Fixo | E11: 120
A12: 09/28 | B12: Plano NENA | D12: Fixo | E12: 288
A13: 09/28 | B13: Internet Casa | D13: Fixo | E13: 135
A14: 09/28 | B14: Parcela Empréstimo LECCA | D14: Fixo | E14: ='💳 Empréstimo'!F35 -> 560 | G14: Parcela 24/36
A17: Total Fixas/Parc. | E17: =SUM(E7:E16) -> 1730
A18: Despesas Gerais (est.) | E18: 1350
A19: TOTAL DESPESAS MÊS | E19: =E17+E18 -> 3080
A21: 🟢 RECEITAS — Set/2028
A22: Data | B22: Descrição | C22: Parcela | D22: Tipo | E22: Valor (R$) | F22: Recebido? | G22: Obs.
A23: 09/28 | B23: Apartamento Rafa | C23: — | D23: Fixo | E23: 1475
A24: 09/28 | B24: Salário Rafa | C24: — | D24: Fixo | E24: 1300
A25: 09/28 | B25: Salário Gabi | C25: — | D25: Fixo | E25: 1500
A29: TOTAL RECEITAS | E29: =SUM(E23:E28) -> 4275
A31: 💡 ANÁLISE RÁPIDA DO MÊS
A32: Saldo do mês: | E32: =E29-E19 -> 1195
A33: Aporte sugerido (20%): | E33: =0.7*(E29-E19) -> 836.5
A34: Reserva de emergência: | E34: =E19/6 -> 513.33333

Sheet Out-28
A1: 💰 FINANÇAS — OUT/2028
A2: 💰 RECEITA TOTAL | C2: 🔴 DESPESAS TOTAL | E2: ✅ SALDO LIVRE | G2: 📊 % SALDO / RECEITA
A3: =E29 -> 4275 | C3: =E19 -> 3080 | E3: =E29-E19 -> 1195 | G3: =IF(E29>0,(E29-E19)/E29,0) -> 0.27953216
A5: 🔴 DESPESAS — Out/2028
A6: Data | B6: Descrição | C6: Parcela | D6: Tipo | E6: Valor (R$) | F6: Pago? | G6: Obs.
A7: 10/28 | B7: Neon Fasomim | C7: Quitado | D7: Parcelado | E7: 86
A8: 10/28 | B8: Plano Cecília | D8: Fixo | E8: 216
A9: 10/28 | B9: Água / Esgoto | D9: Fixo | E9: 230
A10: 10/28 | B10: Energia | D10: Fixo | E10: 95
A11: 10/28 | B11: Celular TIM | D11: Fixo | E11: 120
A12: 10/28 | B12: Plano NENA | D12: Fixo | E12: 288
A13: 10/28 | B13: Internet Casa | D13: Fixo | E13: 135
A14: 10/28 | B14: Parcela Empréstimo LECCA | D14: Fixo | E14: ='💳 Empréstimo'!F36 -> 560 | G14: Parcela 25/36
A17: Total Fixas/Parc. | E17: =SUM(E7:E16) -> 1730
A18: Despesas Gerais (est.) | E18: 1350
A19: TOTAL DESPESAS MÊS | E19: =E17+E18 -> 3080
A21: 🟢 RECEITAS — Out/2028
A22: Data | B22: Descrição | C22: Parcela | D22: Tipo | E22: Valor (R$) | F22: Recebido? | G22: Obs.
A23: 10/28 | B23: Apartamento Rafa | C23: — | D23: Fixo | E23: 1475
A24: 10/28 | B24: Salário Rafa | C24: — | D24: Fixo | E24: 1300
A25: 10/28 | B25: Salário Gabi | C25: — | D25: Fixo | E25: 1500
A29: TOTAL RECEITAS | E29: =SUM(E23:E28) -> 4275
A31: 💡 ANÁLISE RÁPIDA DO MÊS
A32: Saldo do mês: | E32: =E29-E19 -> 1195
A33: Aporte sugerido (20%): | E33: =0.7*(E29-E19) -> 836.5
A34: Reserva de emergência: | E34: =E19/6 -> 513.33333

Sheet Nov-28
A1: 💰 FINANÇAS — NOV/2028
A2: 💰 RECEITA TOTAL | C2: 🔴 DESPESAS TOTAL | E2: ✅ SALDO LIVRE | G2: 📊 % SALDO / RECEITA
A3: =E29 -> 4275 | C3: =E19 -> 3080 | E3: =E29-E19 -> 1195 | G3: =IF(E29>0,(E29-E19)/E29,0) -> 0.27953216
A5: 🔴 DESPESAS — Nov/2028
A6: Data | B6: Descrição | C6: Parcela | D6: Tipo | E6: Valor (R$) | F6: Pago? | G6: Obs.
A7: 11/28 | B7: Neon Fasomim | C7: Quitado | D7: Parcelado | E7: 86
A8: 11/28 | B8: Plano Cecília | D8: Fixo | E8: 216
A9: 11/28 | B9: Água / Esgoto | D9: Fixo | E9: 230
A10: 11/28 | B10: Energia | D10: Fixo | E10: 95
A11: 11/28 | B11: Celular TIM | D11: Fixo | E11: 120
A12: 11/28 | B12: Plano NENA | D12: Fixo | E12: 288
A13: 11/28 | B13: Internet Casa | D13: Fixo | E13: 135
A14: 11/28 | B14: Parcela Empréstimo LECCA | D14: Fixo | E14: ='💳 Empréstimo'!F37 -> 560 | G14: Parcela 26/36
A17: Total Fixas/Parc. | E17: =SUM(E7:E16) -> 1730
A18: Despesas Gerais (est.) | E18: 1350
A19: TOTAL DESPESAS MÊS | E19: =E17+E18 -> 3080
A21: 🟢 RECEITAS — Nov/2028
A22: Data | B22: Descrição | C22: Parcela | D22: Tipo | E22: Valor (R$) | F22: Recebido? | G22: Obs.
A23: 11/28 | B23: Apartamento Rafa | C23: — | D23: Fixo | E23: 1475
A24: 11/28 | B24: Salário Rafa | C24: — | D24: Fixo | E24: 1300
A25: 11/28 | B25: Salário Gabi | C25: — | D25: Fixo | E25: 1500
A29: TOTAL RECEITAS | E29: =SUM(E23:E28) -> 4275
A31: 💡 ANÁLISE RÁPIDA DO MÊS
A32: Saldo do mês: | E32: =E29-E19 -> 1195
A33: Aporte sugerido (20%): | E33: =0.7*(E29-E19) -> 836.5
A34: Reserva de emergência: | E34: =E19/6 -> 513.33333

Sheet Dez-28
A1: 💰 FINANÇAS — DEZ/2028
A2: 💰 RECEITA TOTAL | C2: 🔴 DESPESAS TOTAL | E2: ✅ SALDO LIVRE | G2: 📊 % SALDO / RECEITA
A3: =E29 -> 4275 | C3: =E19 -> 3080 | E3: =E29-E19 -> 1195 | G3: =IF(E29>0,(E29-E19)/E29,0) -> 0.27953216
A5: 🔴 DESPESAS — Dez/2028
A6: Data | B6: Descrição | C6: Parcela | D6: Tipo | E6: Valor (R$) | F6: Pago? | G6: Obs.
A7: 12/28 | B7: Neon Fasomim | C7: Quitado | D7: Parcelado | E7: 86
A8: 12/28 | B8: Plano Cecília | D8: Fixo | E8: 216
A9: 12/28 | B9: Água / Esgoto | D9: Fixo | E9: 230
A10: 12/28 | B10: Energia | D10: Fixo | E10: 95
A11: 12/28 | B11: Celular TIM | D11: Fixo | E11: 120
A12: 12/28 | B12: Plano NENA | D12: Fixo | E12: 288
A13: 12/28 | B13: Internet Casa | D13: Fixo | E13: 135
A14: 12/28 | B14: Parcela Empréstimo LECCA | D14: Fixo | E14: ='💳 Empréstimo'!F38 -> 560 | G14: Parcela 27/36
A17: Total Fixas/Parc. | E17: =SUM(E7:E16) -> 1730
A18: Despesas Gerais (est.) | E18: 1350
A19: TOTAL DESPESAS MÊS | E19: =E17+E18 -> 3080
A21: 🟢 RECEITAS — Dez/2028
A22: Data | B22: Descrição | C22: Parcela | D22: Tipo | E22: Valor (R$) | F22: Recebido? | G22: Obs.
A23: 12/28 | B23: Apartamento Rafa | C23: — | D23: Fixo | E23: 1475
A24: 12/28 | B24: Salário Rafa | C24: — | D24: Fixo | E24: 1300
A25: 12/28 | B25: Salário Gabi | C25: — | D25: Fixo | E25: 1500
A29: TOTAL RECEITAS | E29: =SUM(E23:E28) -> 4275
A31: 💡 ANÁLISE RÁPIDA DO MÊS
A32: Saldo do mês: | E32: =E29-E19 -> 1195
A33: Aporte sugerido (20%): | E33: =0.7*(E29-E19) -> 836.5
A34: Reserva de emergência: | E34: =E19/6 -> 513.33333

Sheet Jan-29
A1: 💰 FINANÇAS — JAN/2029
A2: 💰 RECEITA TOTAL | C2: 🔴 DESPESAS TOTAL | E2: ✅ SALDO LIVRE | G2: 📊 % SALDO / RECEITA
A3: =E29 -> 4275 | C3: =E19 -> 3080 | E3: =E29-E19 -> 1195 | G3: =IF(E29>0,(E29-E19)/E29,0) -> 0.27953216
A5: 🔴 DESPESAS — Jan/2029
A6: Data | B6: Descrição | C6: Parcela | D6: Tipo | E6: Valor (R$) | F6: Pago? | G6: Obs.
A7: 01/29 | B7: Neon Fasomim | C7: Quitado | D7: Parcelado | E7: 86
A8: 01/29 | B8: Plano Cecília | D8: Fixo | E8: 216
A9: 01/29 | B9: Água / Esgoto | D9: Fixo | E9: 230
A10: 01/29 | B10: Energia | D10: Fixo | E10: 95
A11: 01/29 | B11: Celular TIM | D11: Fixo | E11: 120
A12: 01/29 | B12: Plano NENA | D12: Fixo | E12: 288
A13: 01/29 | B13: Internet Casa | D13: Fixo | E13: 135
A14: 01/29 | B14: Parcela Empréstimo LECCA | D14: Fixo | E14: ='💳 Empréstimo'!F39 -> 560 | G14: Parcela 28/36
A17: Total Fixas/Parc. | E17: =SUM(E7:E16) -> 1730
A18: Despesas Gerais (est.) | E18: 1350
A19: TOTAL DESPESAS MÊS | E19: =E17+E18 -> 3080
A21: 🟢 RECEITAS — Jan/2029
A22: Data | B22: Descrição | C22: Parcela | D22: Tipo | E22: Valor (R$) | F22: Recebido? | G22: Obs.
A23: 01/29 | B23: Apartamento Rafa | C23: — | D23: Fixo | E23: 1475
A24: 01/29 | B24: Salário Rafa | C24: — | D24: Fixo | E24: 1300
A25: 01/29 | B25: Salário Gabi | C25: — | D25: Fixo | E25: 1500
A29: TOTAL RECEITAS | E29: =SUM(E23:E28) -> 4275
A31: 💡 ANÁLISE RÁPIDA DO MÊS
A32: Saldo do mês: | E32: =E29-E19 -> 1195
A33: Aporte sugerido (20%): | E33: =0.7*(E29-E19) -> 836.5
A34: Reserva de emergência: | E34: =E19/6 -> 513.33333

Sheet Fev-29
A1: 💰 FINANÇAS — FEV/2029
A2: 💰 RECEITA TOTAL | C2: 🔴 DESPESAS TOTAL | E2: ✅ SALDO LIVRE | G2: 📊 % SALDO / RECEITA
A3: =E29 -> 4275 | C3: =E19 -> 3080 | E3: =E29-E19 -> 1195 | G3: =IF(E29>0,(E29-E19)/E29,0) -> 0.27953216
A5: 🔴 DESPESAS — Fev/2029
A6: Data | B6: Descrição | C6: Parcela | D6: Tipo | E6: Valor (R$) | F6: Pago? | G6: Obs.
A7: 02/29 | B7: Neon Fasomim | C7: Quitado | D7: Parcelado | E7: 86
A8: 02/29 | B8: Plano Cecília | D8: Fixo | E8: 216
A9: 02/29 | B9: Água / Esgoto | D9: Fixo | E9: 230
A10: 02/29 | B10: Energia | D10: Fixo | E10: 95
A11: 02/29 | B11: Celular TIM | D11: Fixo | E11: 120
A12: 02/29 | B12: Plano NENA | D12: Fixo | E12: 288
A13: 02/29 | B13: Internet Casa | D13: Fixo | E13: 135
A14: 02/29 | B14: Parcela Empréstimo LECCA | D14: Fixo | E14: ='💳 Empréstimo'!F40 -> 560 | G14: Parcela 29/36
A17: Total Fixas/Parc. | E17: =SUM(E7:E16) -> 1730
A18: Despesas Gerais (est.) | E18: 1350
A19: TOTAL DESPESAS MÊS | E19: =E17+E18 -> 3080
A21: 🟢 RECEITAS — Fev/2029
A22: Data | B22: Descrição | C22: Parcela | D22: Tipo | E22: Valor (R$) | F22: Recebido? | G22: Obs.
A23: 02/29 | B23: Apartamento Rafa | C23: — | D23: Fixo | E23: 1475
A24: 02/29 | B24: Salário Rafa | C24: — | D24: Fixo | E24: 1300
A25: 02/29 | B25: Salário Gabi | C25: — | D25: Fixo | E25: 1500
A29: TOTAL RECEITAS | E29: =SUM(E23:E28) -> 4275
A31: 💡 ANÁLISE RÁPIDA DO MÊS
A32: Saldo do mês: | E32: =E29-E19 -> 1195
A33: Aporte sugerido (20%): | E33: =0.7*(E29-E19) -> 836.5
A34: Reserva de emergência: | E34: =E19/6 -> 513.33333

Sheet Mar-29
A1: 💰 FINANÇAS — MAR/2029
A2: 💰 RECEITA TOTAL | C2: 🔴 DESPESAS TOTAL | E2: ✅ SALDO LIVRE | G2: 📊 % SALDO / RECEITA
A3: =E29 -> 4275 | C3: =E19 -> 3080 | E3: =E29-E19 -> 1195 | G3: =IF(E29>0,(E29-E19)/E29,0) -> 0.27953216
A5: 🔴 DESPESAS — Mar/2029
A6: Data | B6: Descrição | C6: Parcela | D6: Tipo | E6: Valor (R$) | F6: Pago? | G6: Obs.
A7: 03/29 | B7: Neon Fasomim | C7: Quitado | D7: Parcelado | E7: 86
A8: 03/29 | B8: Plano Cecília | D8: Fixo | E8: 216
A9: 03/29 | B9: Água / Esgoto | D9: Fixo | E9: 230
A10: 03/29 | B10: Energia | D10: Fixo | E10: 95
A11: 03/29 | B11: Celular TIM | D11: Fixo | E11: 120
A12: 03/29 | B12: Plano NENA | D12: Fixo | E12: 288
A13: 03/29 | B13: Internet Casa | D13: Fixo | E13: 135
A14: 03/29 | B14: Parcela Empréstimo LECCA | D14: Fixo | E14: ='💳 Empréstimo'!F41 -> 560 | G14: Parcela 30/36
A17: Total Fixas/Parc. | E17: =SUM(E7:E16) -> 1730
A18: Despesas Gerais (est.) | E18: 1350
A19: TOTAL DESPESAS MÊS | E19: =E17+E18 -> 3080
A21: 🟢 RECEITAS — Mar/2029
A22: Data | B22: Descrição | C22: Parcela | D22: Tipo | E22: Valor (R$) | F22: Recebido? | G22: Obs.
A23: 03/29 | B23: Apartamento Rafa | C23: — | D23: Fixo | E23: 1475
A24: 03/29 | B24: Salário Rafa | C24: — | D24: Fixo | E24: 1300
A25: 03/29 | B25: Salário Gabi | C25: — | D25: Fixo | E25: 1500
A29: TOTAL RECEITAS | E29: =SUM(E23:E28) -> 4275
A31: 💡 ANÁLISE RÁPIDA DO MÊS
A32: Saldo do mês: | E32: =E29-E19 -> 1195
A33: Aporte sugerido (20%): | E33: =0.7*(E29-E19) -> 836.5
A34: Reserva de emergência: | E34: =E19/6 -> 513.33333

Sheet Abr-29
A1: 💰 FINANÇAS — ABR/2029
A2: 💰 RECEITA TOTAL | C2: 🔴 DESPESAS TOTAL | E2: ✅ SALDO LIVRE | G2: 📊 % SALDO / RECEITA
A3: =E29 -> 4275 | C3: =E19 -> 3080 | E3: =E29-E19 -> 1195 | G3: =IF(E29>0,(E29-E19)/E29,0) -> 0.27953216
A5: 🔴 DESPESAS — Abr/2029
A6: Data | B6: Descrição | C6: Parcela | D6: Tipo | E6: Valor (R$) | F6: Pago? | G6: Obs.
A7: 04/29 | B7: Neon Fasomim | C7: Quitado | D7: Parcelado | E7: 86
A8: 04/29 | B8: Plano Cecília | D8: Fixo | E8: 216
A9: 04/29 | B9: Água / Esgoto | D9: Fixo | E9: 230
A10: 04/29 | B10: Energia | D10: Fixo | E10: 95
A11: 04/29 | B11: Celular TIM | D11: Fixo | E11: 120
A12: 04/29 | B12: Plano NENA | D12: Fixo | E12: 288
A13: 04/29 | B13: Internet Casa | D13: Fixo | E13: 135
A14: 04/29 | B14: Parcela Empréstimo LECCA | D14: Fixo | E14: ='💳 Empréstimo'!F42 -> 560 | G14: Parcela 31/36
A17: Total Fixas/Parc. | E17: =SUM(E7:E16) -> 1730
A18: Despesas Gerais (est.) | E18: 1350
A19: TOTAL DESPESAS MÊS | E19: =E17+E18 -> 3080
A21: 🟢 RECEITAS — Abr/2029
A22: Data | B22: Descrição | C22: Parcela | D22: Tipo | E22: Valor (R$) | F22: Recebido? | G22: Obs.
A23: 04/29 | B23: Apartamento Rafa | C23: — | D23: Fixo | E23: 1475
A24: 04/29 | B24: Salário Rafa | C24: — | D24: Fixo | E24: 1300
A25: 04/29 | B25: Salário Gabi | C25: — | D25: Fixo | E25: 1500
A29: TOTAL RECEITAS | E29: =SUM(E23:E28) -> 4275
A31: 💡 ANÁLISE RÁPIDA DO MÊS
A32: Saldo do mês: | E32: =E29-E19 -> 1195
A33: Aporte sugerido (20%): | E33: =0.7*(E29-E19) -> 836.5
A34: Reserva de emergência: | E34: =E19/6 -> 513.33333

Sheet Mai-29
A1: 💰 FINANÇAS — MAI/2029
A2: 💰 RECEITA TOTAL | C2: 🔴 DESPESAS TOTAL | E2: ✅ SALDO LIVRE | G2: 📊 % SALDO / RECEITA
A3: =E29 -> 4275 | C3: =E19 -> 3080 | E3: =E29-E19 -> 1195 | G3: =IF(E29>0,(E29-E19)/E29,0) -> 0.27953216
A5: 🔴 DESPESAS — Mai/2029
A6: Data | B6: Descrição | C6: Parcela | D6: Tipo | E6: Valor (R$) | F6: Pago? | G6: Obs.
A7: 05/29 | B7: Neon Fasomim | C7: Quitado | D7: Parcelado | E7: 86
A8: 05/29 | B8: Plano Cecília | D8: Fixo | E8: 216
A9: 05/29 | B9: Água / Esgoto | D9: Fixo | E9: 230
A10: 05/29 | B10: Energia | D10: Fixo | E10: 95
A11: 05/29 | B11: Celular TIM | D11: Fixo | E11: 120
A12: 05/29 | B12: Plano NENA | D12: Fixo | E12: 288
A13: 05/29 | B13: Internet Casa | D13: Fixo | E13: 135
A14: 05/29 | B14: Parcela Empréstimo LECCA | D14: Fixo | E14: ='💳 Empréstimo'!F43 -> 560 | G14: Parcela 32/36
A17: Total Fixas/Parc. | E17: =SUM(E7:E16) -> 1730
A18: Despesas Gerais (est.) | E18: 1350
A19: TOTAL DESPESAS MÊS | E19: =E17+E18 -> 3080
A21: 🟢 RECEITAS — Mai/2029
A22: Data | B22: Descrição | C22: Parcela | D22: Tipo | E22: Valor (R$) | F22: Recebido? | G22: Obs.
A23: 05/29 | B23: Apartamento Rafa | C23: — | D23: Fixo | E23: 1475
A24: 05/29 | B24: Salário Rafa | C24: — | D24: Fixo | E24: 1300
A25: 05/29 | B25: Salário Gabi | C25: — | D25: Fixo | E25: 1500
A29: TOTAL RECEITAS | E29: =SUM(E23:E28) -> 4275
A31: 💡 ANÁLISE RÁPIDA DO MÊS
A32: Saldo do mês: | E32: =E29-E19 -> 1195
A33: Aporte sugerido (20%): | E33: =0.7*(E29-E19) -> 836.5
A34: Reserva de emergência: | E34: =E19/6 -> 513.33333

Sheet Jun-29
A1: 💰 FINANÇAS — JUN/2029
A2: 💰 RECEITA TOTAL | C2: 🔴 DESPESAS TOTAL | E2: ✅ SALDO LIVRE | G2: 📊 % SALDO / RECEITA
A3: =E29 -> 4275 | C3: =E19 -> 3080 | E3: =E29-E19 -> 1195 | G3: =IF(E29>0,(E29-E19)/E29,0) -> 0.27953216
A5: 🔴 DESPESAS — Jun/2029
A6: Data | B6: Descrição | C6: Parcela | D6: Tipo | E6: Valor (R$) | F6: Pago? | G6: Obs.
A7: 06/29 | B7: Neon Fasomim | C7: Quitado | D7: Parcelado | E7: 86
A8: 06/29 | B8: Plano Cecília | D8: Fixo | E8: 216
A9: 06/29 | B9: Água / Esgoto | D9: Fixo | E9: 230
A10: 06/29 | B10: Energia | D10: Fixo | E10: 95
A11: 06/29 | B11: Celular TIM | D11: Fixo | E11: 120
A12: 06/29 | B12: Plano NENA | D12: Fixo | E12: 288
A13: 06/29 | B13: Internet Casa | D13: Fixo | E13: 135
A14: 06/29 | B14: Parcela Empréstimo LECCA | D14: Fixo | E14: ='💳 Empréstimo'!F44 -> 560 | G14: Parcela 33/36
A17: Total Fixas/Parc. | E17: =SUM(E7:E16) -> 1730
A18: Despesas Gerais (est.) | E18: 1350
A19: TOTAL DESPESAS MÊS | E19: =E17+E18 -> 3080
A21: 🟢 RECEITAS — Jun/2029
A22: Data | B22: Descrição | C22: Parcela | D22: Tipo | E22: Valor (R$) | F22: Recebido? | G22: Obs.
A23: 06/29 | B23: Apartamento Rafa | C23: — | D23: Fixo | E23: 1475
A24: 06/29 | B24: Salário Rafa | C24: — | D24: Fixo | E24: 1300
A25: 06/29 | B25: Salário Gabi | C25: — | D25: Fixo | E25: 1500
A29: TOTAL RECEITAS | E29: =SUM(E23:E28) -> 4275
A31: 💡 ANÁLISE RÁPIDA DO MÊS
A32: Saldo do mês: | E32: =E29-E19 -> 1195
A33: Aporte sugerido (20%): | E33: =0.7*(E29-E19) -> 836.5
A34: Reserva de emergência: | E34: =E19/6 -> 513.33333

Sheet Jul-29
A1: 💰 FINANÇAS — JUL/2029
A2: 💰 RECEITA TOTAL | C2: 🔴 DESPESAS TOTAL | E2: ✅ SALDO LIVRE | G2: 📊 % SALDO / RECEITA
A3: =E29 -> 4275 | C3: =E19 -> 3080 | E3: =E29-E19 -> 1195 | G3: =IF(E29>0,(E29-E19)/E29,0) -> 0.27953216
A5: 🔴 DESPESAS — Jul/2029
A6: Data | B6: Descrição | C6: Parcela | D6: Tipo | E6: Valor (R$) | F6: Pago? | G6: Obs.
A7: 07/29 | B7: Neon Fasomim | C7: Quitado | D7: Parcelado | E7: 86
A8: 07/29 | B8: Plano Cecília | D8: Fixo | E8: 216
A9: 07/29 | B9: Água / Esgoto | D9: Fixo | E9: 230
A10: 07/29 | B10: Energia | D10: Fixo | E10: 95
A11: 07/29 | B11: Celular TIM | D11: Fixo | E11: 120
A12: 07/29 | B12: Plano NENA | D12: Fixo | E12: 288
A13: 07/29 | B13: Internet Casa | D13: Fixo | E13: 135
A14: 07/29 | B14: Parcela Empréstimo LECCA | D14: Fixo | E14: ='💳 Empréstimo'!F45 -> 560 | G14: Parcela 34/36
A17: Total Fixas/Parc. | E17: =SUM(E7:E16) -> 1730
A18: Despesas Gerais (est.) | E18: 1350
A19: TOTAL DESPESAS MÊS | E19: =E17+E18 -> 3080
A21: 🟢 RECEITAS — Jul/2029
A22: Data | B22: Descrição | C22: Parcela | D22: Tipo | E22: Valor (R$) | F22: Recebido? | G22: Obs.
A23: 07/29 | B23: Apartamento Rafa | C23: — | D23: Fixo | E23: 1475
A24: 07/29 | B24: Salário Rafa | C24: — | D24: Fixo | E24: 1300
A25: 07/29 | B25: Salário Gabi | C25: — | D25: Fixo | E25: 1500
A29: TOTAL RECEITAS | E29: =SUM(E23:E28) -> 4275
A31: 💡 ANÁLISE RÁPIDA DO MÊS
A32: Saldo do mês: | E32: =E29-E19 -> 1195
A33: Aporte sugerido (20%): | E33: =0.7*(E29-E19) -> 836.5
A34: Reserva de emergência: | E34: =E19/6 -> 513.33333

Sheet Ago-29
A1: 💰 FINANÇAS — AGO/2029
A2: 💰 RECEITA TOTAL | C2: 🔴 DESPESAS TOTAL | E2: ✅ SALDO LIVRE | G2: 📊 % SALDO / RECEITA
A3: =E29 -> 4275 | C3: =E19 -> 3080 | E3: =E29-E19 -> 1195 | G3: =IF(E29>0,(E29-E19)/E29,0) -> 0.27953216
A5: 🔴 DESPESAS — Ago/2029
A6: Data | B6: Descrição | C6: Parcela | D6: Tipo | E6: Valor (R$) | F6: Pago? | G6: Obs.
A7: 08/29 | B7: Neon Fasomim | C7: Quitado | D7: Parcelado | E7: 86
A8: 08/29 | B8: Plano Cecília | D8: Fixo | E8: 216
A9: 08/29 | B9: Água / Esgoto | D9: Fixo | E9: 230
A10: 08/29 | B10: Energia | D10: Fixo | E10: 95
A11: 08/29 | B11: Celular TIM | D11: Fixo | E11: 120
A12: 08/29 | B12: Plano NENA | D12: Fixo | E12: 288
A13: 08/29 | B13: Internet Casa | D13: Fixo | E13: 135
A14: 08/29 | B14: Parcela Empréstimo LECCA | D14: Fixo | E14: ='💳 Empréstimo'!F46 -> 560 | G14: Parcela 35/36
A17: Total Fixas/Parc. | E17: =SUM(E7:E16) -> 1730
A18: Despesas Gerais (est.) | E18: 1350
A19: TOTAL DESPESAS MÊS | E19: =E17+E18 -> 3080
A21: 🟢 RECEITAS — Ago/2029
A22: Data | B22: Descrição | C22: Parcela | D22: Tipo | E22: Valor (R$) | F22: Recebido? | G22: Obs.
A23: 08/29 | B23: Apartamento Rafa | C23: — | D23: Fixo | E23: 1475
A24: 08/29 | B24: Salário Rafa | C24: — | D24: Fixo | E24: 1300
A25: 08/29 | B25: Salário Gabi | C25: — | D25: Fixo | E25: 1500
A29: TOTAL RECEITAS | E29: =SUM(E23:E28) -> 4275
A31: 💡 ANÁLISE RÁPIDA DO MÊS
A32: Saldo do mês: | E32: =E29-E19 -> 1195
A33: Aporte sugerido (20%): | E33: =0.7*(E29-E19) -> 836.5
A34: Reserva de emergência: | E34: =E19/6 -> 513.33333

Sheet Set-29
A1: 💰 FINANÇAS — SET/2029
A2: 💰 RECEITA TOTAL | C2: 🔴 DESPESAS TOTAL | E2: ✅ SALDO LIVRE | G2: 📊 % SALDO / RECEITA
A3: =E29 -> 4275 | C3: =E19 -> 3967.4236 | E3: =E29-E19 -> 307.57644 | G3: =IF(E29>0,(E29-E19)/E29,0) -> 0.071947704
A5: 🔴 DESPESAS — Set/2029
A6: Data | B6: Descrição | C6: Parcela | D6: Tipo | E6: Valor (R$) | F6: Pago? | G6: Obs.
A7: 09/29 | B7: Neon Fasomim | C7: Quitado | D7: Parcelado | E7: 86
A8: 09/29 | B8: Plano Cecília | D8: Fixo | E8: 216
A9: 09/29 | B9: Água / Esgoto | D9: Fixo | E9: 230
A10: 09/29 | B10: Energia | D10: Fixo | E10: 95
A11: 09/29 | B11: Celular TIM | D11: Fixo | E11: 120
A12: 09/29 | B12: Plano NENA | D12: Fixo | E12: 288
A13: 09/29 | B13: Internet Casa | D13: Fixo | E13: 135
A14: 09/29 | B14: Parcela Empréstimo LECCA | D14: Fixo | E14: ='💳 Empréstimo'!F47 -> 1447.4236 | G14: Parcela 36/36
A17: Total Fixas/Parc. | E17: =SUM(E7:E16) -> 2617.4236
A18: Despesas Gerais (est.) | E18: 1350
A19: TOTAL DESPESAS MÊS | E19: =E17+E18 -> 3967.4236
A21: 🟢 RECEITAS — Set/2029
A22: Data | B22: Descrição | C22: Parcela | D22: Tipo | E22: Valor (R$) | F22: Recebido? | G22: Obs.
A23: 09/29 | B23: Apartamento Rafa | C23: — | D23: Fixo | E23: 1475
A24: 09/29 | B24: Salário Rafa | C24: — | D24: Fixo | E24: 1300
A25: 09/29 | B25: Salário Gabi | C25: — | D25: Fixo | E25: 1500
A29: TOTAL RECEITAS | E29: =SUM(E23:E28) -> 4275
A31: 💡 ANÁLISE RÁPIDA DO MÊS
A32: Saldo do mês: | E32: =E29-E19 -> 307.57644
A33: Aporte sugerido (20%): | E33: =0.7*(E29-E19) -> 215.3035
A34: Reserva de emergência: | E34: =E19/6 -> 661.23726

Sheet 💳 Empréstimo
A1: 💳 CONTROLE DE EMPRÉSTIMO — Proposta LECCA (36 meses)
A2: ⚙️ PREMISSAS — Altere os valores em azul
A3: Valor financiado (R$) | B3: 13600 | C3: Valor liberado conforme proposta LECCA
A4: Juros total do empréstimo (R$) | B4: =D48 -> 7447.4236 | C4: Total de juros pagos em 36 meses (era usado para somar ao aporte de Set/26 — agora usado no cruzamento com o rendimento)
A5: Parcela mensal (R$) | B5: 560 | C5: Valor fixo informado na proposta
A6: Prazo (meses) | B6: 36
A7: CET informado (a.m. / a.a.) | B7: 0.0243 | C7: 2,43% a.m. / 33,94% a.a. — Custo Efetivo Total, já com IOF
A8: Taxa efetiva usada nos cálculos (a.m.) | B8: 0.024799212 | C8: Taxa que reconcilia valor financiado, parcela e prazo informados (pequena dif. do CET nominal por arredondamento/IOF embutido)
A9: Data de liberação do crédito | B9: 46266 | C9: 1ª parcela vence no mês seguinte (Out/26)
A10: Juros médio mensal (R$) | B10: =B4/36 -> 206.87288 | C10: Juros total ÷ 36 meses — usado como custo mensal médio no cruzamento com o rendimento (aba 📊 Cruzamento)
A11: Mês | B11: Data | C11: Saldo Inicial (R$) | D11: Juros do Mês (R$) | E11: Amortização (R$) | F11: Parcela (R$) | G11: Saldo Final (R$)
A12: 1 | B12: =EDATE($B$9,1) -> 46296 | C12: =$B$3 -> 13600 | D12: =C12*$B$8 -> 337.26928 | E12: =IF(A12=$B$6,C12,$B$5-D12) -> 222.73072 | F12: =IF(A12=$B$6,E12+D12,$B$5) -> 560 | G12: =MAX(C12-E12,0) -> 13377.269
A13: 2 | B13: =EDATE(B12,1) -> 46327 | C13: =G12 -> 13377.269 | D13: =C13*$B$8 -> 331.74573 | E13: =IF(A13=$B$6,C13,$B$5-D13) -> 228.25427 | F13: =IF(A13=$B$6,E13+D13,$B$5) -> 560 | G13: =MAX(C13-E13,0) -> 13149.015
A14: 3 | B14: =EDATE(B13,1) -> 46357 | C14: =G13 -> 13149.015 | D14: =C14*$B$8 -> 326.08521 | E14: =IF(A14=$B$6,C14,$B$5-D14) -> 233.91479 | F14: =IF(A14=$B$6,E14+D14,$B$5) -> 560 | G14: =MAX(C14-E14,0) -> 12915.1
A15: 4 | B15: =EDATE(B14,1) -> 46388 | C15: =G14 -> 12915.1 | D15: =C15*$B$8 -> 320.28431 | E15: =IF(A15=$B$6,C15,$B$5-D15) -> 239.71569 | F15: =IF(A15=$B$6,E15+D15,$B$5) -> 560 | G15: =MAX(C15-E15,0) -> 12675.385
A16: 5 | B16: =EDATE(B15,1) -> 46419 | C16: =G15 -> 12675.385 | D16: =C16*$B$8 -> 314.33954 | E16: =IF(A16=$B$6,C16,$B$5-D16) -> 245.66046 | F16: =IF(A16=$B$6,E16+D16,$B$5) -> 560 | G16: =MAX(C16-E16,0) -> 12429.724
A17: 6 | B17: =EDATE(B16,1) -> 46447 | C17: =G16 -> 12429.724 | D17: =C17*$B$8 -> 308.24736 | E17: =IF(A17=$B$6,C17,$B$5-D17) -> 251.75264 | F17: =IF(A17=$B$6,E17+D17,$B$5) -> 560 | G17: =MAX(C17-E17,0) -> 12177.971
A18: 7 | B18: =EDATE(B17,1) -> 46478 | C18: =G17 -> 12177.971 | D18: =C18*$B$8 -> 302.00409 | E18: =IF(A18=$B$6,C18,$B$5-D18) -> 257.99591 | F18: =IF(A18=$B$6,E18+D18,$B$5) -> 560 | G18: =MAX(C18-E18,0) -> 11919.976
A19: 8 | B19: =EDATE(B18,1) -> 46508 | C19: =G18 -> 11919.976 | D19: =C19*$B$8 -> 295.606 | E19: =IF(A19=$B$6,C19,$B$5-D19) -> 264.394 | F19: =IF(A19=$B$6,E19+D19,$B$5) -> 560 | G19: =MAX(C19-E19,0) -> 11655.582
A20: 9 | B20: =EDATE(B19,1) -> 46539 | C20: =G19 -> 11655.582 | D20: =C20*$B$8 -> 289.04923 | E20: =IF(A20=$B$6,C20,$B$5-D20) -> 270.95077 | F20: =IF(A20=$B$6,E20+D20,$B$5) -> 560 | G20: =MAX(C20-E20,0) -> 11384.631
A21: 10 | B21: =EDATE(B20,1) -> 46569 | C21: =G20 -> 11384.631 | D21: =C21*$B$8 -> 282.32987 | E21: =IF(A21=$B$6,C21,$B$5-D21) -> 277.67013 | F21: =IF(A21=$B$6,E21+D21,$B$5) -> 560 | G21: =MAX(C21-E21,0) -> 11106.961
A22: 11 | B22: =EDATE(B21,1) -> 46600 | C22: =G21 -> 11106.961 | D22: =C22*$B$8 -> 275.44387 | E22: =IF(A22=$B$6,C22,$B$5-D22) -> 284.55613 | F22: =IF(A22=$B$6,E22+D22,$B$5) -> 560 | G22: =MAX(C22-E22,0) -> 10822.404
A23: 12 | B23: =EDATE(B22,1) -> 46631 | C23: =G22 -> 10822.404 | D23: =C23*$B$8 -> 268.3871 | E23: =IF(A23=$B$6,C23,$B$5-D23) -> 291.6129 | F23: =IF(A23=$B$6,E23+D23,$B$5) -> 560 | G23: =MAX(C23-E23,0) -> 10530.792
A24: 13 | B24: =EDATE(B23,1) -> 46661 | C24: =G23 -> 10530.792 | D24: =C24*$B$8 -> 261.15533 | E24: =IF(A24=$B$6,C24,$B$5-D24) -> 298.84467 | F24: =IF(A24=$B$6,E24+D24,$B$5) -> 560 | G24: =MAX(C24-E24,0) -> 10231.947
... A47: 36 | B47: =EDATE(B46,1) -> 47362 | C47: =G46 -> 1412.3972 | D47: =C47*$B$8 -> 35.026338 | E47: =IF(A47=$B$6,C47,$B$5-D47) -> 1412.3972 | F47: =IF(A47=$B$6,E47+D47,$B$5) -> 1447.4236 | G47: =MAX(C47-E47,0) -> 0
A48: TOTAL | D48: =SUM(D12:D47) -> 7447.4236 | E48: =SUM(E12:E47) -> 13600 | F48: =SUM(F12:F47) -> 21047.424 | G48: 0
A50: Custo total do dinheiro (juros pagos em 36 meses): | D50: =D48 -> 7447.4236

Sheet 📊 Cruzamento J x R
A1: 📊 CRUZAMENTO: JUROS DO EMPRÉSTIMO vs. RENDIMENTO DO INVESTIMENTO (Set/26 a Ago/29)
A2: ⚙️ PREMISSAS — Altere os valores em azul
A3: Saldo inicial investido (R$) | B3: 13000 | C3: Reserva acumulada + valor do empréstimo aplicado em Set/26
A4: Aporte mensal (R$) | B4: 1500 | C4: Aporte reduzido (vs. R$ 2.000) para caber a parcela do empréstimo no orçamento
A5: Rendimento mensal (CDB/Selic) | B5: 0.0116 | C5: Rendimento mensal (CDB/Selic)
A6: Data de início (Mês 1) | B6: 46296 | C6: Alinhado ao vencimento da 1ª parcela do empréstimo
A7: Nesta versão, o juro do empréstimo é tratado como custo médio mensal fixo (juros totais ÷ 36), não a curva real decrescente da amortização — ver aba 💳 Empréstimo para o valor exato mês a mês.
A8: Mês | B8: Data | C8: Juros Empréstimo/Mês (R$) | D8: Rendimento Investimento/Mês (R$) | E8: Diferença Rend. − Juros (R$) | F8: Saldo Investimento Acum. (R$)
A9: 1 | B9: =$B$6 -> 46296 | C9: ='💳 Empréstimo'!$B$10 -> 206.87288 | D9: =$B$3*$B$5 -> 150.8 | E9: =D9-C9 -> -56.072877 | F9: =$B$3+$B$4+D9 -> 14650.8
A10: 2 | B10: =EDATE(B9,1) -> 46327 | C10: ='💳 Empréstimo'!$B$10 -> 206.87288 | D10: =F9*$B$5 -> 169.94928 | E10: =D10-C10 -> -36.923597 | F10: =F9+$B$4+D10 -> 16320.749
A11: 3 | B11: =EDATE(B10,1) -> 46357 | C11: ='💳 Empréstimo'!$B$10 -> 206.87288 | D11: =F10*$B$5 -> 189.32069 | E11: =D11-C11 -> -17.552185 | F11: =F10+$B$4+D11 -> 18010.07
A12: 4 | B12: =EDATE(B11,1) -> 46388 | C12: ='💳 Empréstimo'!$B$10 -> 206.87288 | D12: =F11*$B$5 -> 208.91681 | E12: =D12-C12 -> 2.0439349 | F12: =F11+$B$4+D12 -> 19718.987
A13: 5 | B13: =EDATE(B12,1) -> 46419 | C13: ='💳 Empréstimo'!$B$10 -> 206.87288 | D13: =F12*$B$5 -> 228.74025 | E13: =D13-C13 -> 21.86737 | F13: =F12+$B$4+D13 -> 21447.727
A14: 6 | B14: =EDATE(B13,1) -> 46447 | C14: ='💳 Empréstimo'!$B$10 -> 206.87288 | D14: =F13*$B$5 -> 248.79363 | E14: =D14-C14 -> 41.920757 | F14: =F13+$B$4+D14 -> 23196.521
A15: 7 | B15: =EDATE(B14,1) -> 46478 | C15: ='💳 Empréstimo'!$B$10 -> 206.87288 | D15: =F14*$B$5 -> 269.07964 | E15: =D15-C15 -> 62.206763 | F15: =F14+$B$4+D15 -> 24965.6
A16: 8 | B16: =EDATE(B15,1) -> 46508 | C16: ='💳 Empréstimo'!$B$10 -> 206.87288 | D16: =F15*$B$5 -> 289.60096 | E16: =D16-C16 -> 82.728087 | F16: =F15+$B$4+D16 -> 26755.201
A17: 9 | B17: =EDATE(B16,1) -> 46539 | C17: ='💳 Empréstimo'!$B$10 -> 206.87288 | D17: =F16*$B$5 -> 310.36033 | E17: =D17-C17 -> 103.48746 | F17: =F16+$B$4+D17 -> 28565.562
A18: 10 | B18: =EDATE(B17,1) -> 46569 | C18: ='💳 Empréstimo'!$B$10 -> 206.87288 | D18: =F17*$B$5 -> 331.36051 | E18: =D18-C18 -> 124.48764 | F18: =F17+$B$4+D18 -> 30396.922
A19: 11 | B19: =EDATE(B18,1) -> 46600 | C19: ='💳 Empréstimo'!$B$10 -> 206.87288 | D19: =F18*$B$5 -> 352.6043 | E19: =D19-C19 -> 145.73142 | F19: =F18+$B$4+D19 -> 32249.526
A20: 12 | B20: =EDATE(B19,1) -> 46631 | C20: ='💳 Empréstimo'!$B$10 -> 206.87288 | D20: =F19*$B$5 -> 374.09451 | E20: =D20-C20 -> 167.22163 | F20: =F19+$B$4+D20 -> 34123.621
A21: 13 | B21: =EDATE(B20,1) -> 46661 | C21: ='💳 Empréstimo'!$B$10 -> 206.87288 | D21: =F20*$B$5 -> 395.834 | E21: =D21-C21 -> 188.96113 | F21: =F20+$B$4+D21 -> 36019.455
... A44: 36 | B44: =EDATE(B43,1) -> 47362 | C44: ='💳 Empréstimo'!$B$10 -> 206.87288 | D44: =F43*$B$5 -> 971.74226 | E44: =D44-C44 -> 764.86939 | F44: =F43+$B$4+D44 -> 86242.627
A45: TOTAL / SALDO FINAL | C45: =SUM(C9:C44) -> 7447.4236 | D45: =SUM(D9:D44) -> 19242.627 | E45: =D45-C45 -> 11795.204 | F45: =F44 -> 86242.627
A47: Mês em que o rendimento passa a superar o juro do mês: | E47: {=MATCH(TRUE(),INDEX(D9:D44>C9:C44,0),0)} -> 4
A48: Análise: até o cruzamento, o custo do empréstimo pesa mais no caixa; depois dele, o rendimento do investimento gera mais do que o juro cobra por mês. No acumulado dos 36 meses, o rendimento total supera o custo total do empréstimo.

Sheet ✂️ Redução Custos
A1: ✂️ PLANO DE REDUÇÃO DE CUSTOS
A2: Despesa | B2: Atual (R$) | C2: Meta (R$) | D2: Economia/mês | E2: Status | F2: Ação
A3: Celular TIM | B3: 120 | C3: 70 | D3: =B3-C3 -> 50 | E3: 🟡 Pendente | F3: Migrar para operadora digital (Claro/Vivo/C6)
A4: Plano NENA | B4: 288 | C4: 180 | D4: =B4-C4 -> 108 | E4: ✅ OK | F4: inegociavel
A5: Plano Cecília | B5: 216 | C5: 160 | D5: =B5-C5 -> 56 | E5: ✅ OK | F5: Verificar plano familiar/combo com NENA
A6: Internet Casa | B6: 135 | C6: 100 | D6: =B6-C6 -> 35 | E6: 🟡 Pendente | F6: Negociar fidelidade ou trocar provedor
A7: Energia | B7: 250 | C7: 200 | D7: =B7-C7 -> 50 | E7: 🟡 Pendente | F7: Hábitos de consumo / lâmpadas LED
A8: Água / Esgoto | B8: 230 | C8: 230 | D8: =B8-C8 -> 0 | E8: ✅ OK | F8: Sem ação imediata — custo fixo externo
A9: Neon Fasomim | B9: 86 | C9: 86 | D9: =B9-C9 -> 0 | E9: ⏳ Quitando | F9: Parcelado — aguardar quitação (3 parcelas)
A10: TOTAL | B10: =SUM(B3:B9) -> 1325 | C10: =SUM(C3:C9) -> 1026 | D10: =SUM(D3:D9) -> 299

Sheet 💡 Análise
A1: 💡 ANÁLISE & RECOMENDAÇÕES
A2: Ícone | B2: Tópico | C2: Detalhe
A3: ✅ | B3: Regra 50/30/20 para investir | C3: Sobre R$ 4.525 recorrentes → R$ 1800/mês investidos. Em 12 meses = ~R$ 10.860 + juros compostos.
A4: 🚨 | B4: Perda do Seguro Gabi em Jul/2025 | C4: Receita cai R$ 1.371/mês a partir de julho. Renda recorrente: ~R$ 4.525. Planeje AGORA.
A5: ⚠️ | B5: Plano NENA custa R$ 288 | C5: É a despesa mais cara. Pesquise alternativas ou negocie. Economia potencial: R$ 80–120/mês.
A6: ⚠️ | B6: Celular TIM R$ 120 | C6: Planos de R$ 60–80 com boa franquia existem. Migrar pode economizar ~R$ 40–60/mês.
A7: 💡 | B7: Dois planos: Cecília + NENA | C7: R$ 216 + R$ 288 = R$ 504. Verifique plano familiar/combo para economizar.
A8: 🏦 | B8: Prioridade: Reserva de Emergência | C8: Meta: R$ 15.000 (6× despesas). CDB liquidez diária ou Tesouro Selic. Prioridade máxima.
A9: 📈 | B9: Próximo passo: Tesouro / CDBs | C9: Renda fixa segura enquanto aprende. Tesouro Selic p/ liquidez, CDB p/ prazo.
A10: 📊 | B10: Longo prazo: Fundos Indexados | C10: IVVB11 (S&P500 em BRL) e BOVA11 (Ibovespa). Diversificação simples no longo prazo.
A13: ✅ SUAS 3 AÇÕES DESTA SEMANA
A14: 1 | B14: Hoje | C14: Descubra o que é o Plano NENA e pesquise 2 alternativas mais baratas
A15: 2 | B15: Esta semana | C15: Simule portabilidade do TIM para Claro/Vivo/C6 — economia ~R$ 50/mês
A16: 3 | B16: Antes de Julho | C16: Separe R$ 1800 em conta separada no dia do salário — ANTES de gastar qualquer coisa

Sheet Planilha2
